{
  "neighborhood_name": "מורד הנחל",
  "city_name": "שלומי",
  "transaction_count": 37,
  "transactions": [
    {
      "assetId": 4335207.0,
      "addressId": 0,
      "polygonId": "18221-435",
      "neighborhoodName": "מורד הנחל",
      "neighborhoodId": 65210465,
      "address": "0",
      "dealDate": "2025-05-14",
      "dealAmount": 1500000,
      "parcelNum": "18221-435-2",
      "dealNature": "דירה בבית קומות",
      "roomNum": 4.5,
      "floor": null,
      "assetArea": 147.0,
      "yearBuilt": 0,
      "streetCode": 0,
      "settlmentID": 812,
      "buildingFloors": 0,
      "hokHamecher": 0,
      "trend": {
        "rate": 0,
        "years": 0
      },
      "prevDeals": [],
      "ownership": [],
      "priceSM": 10204,
      "row_id": 1
    },
    {
      "assetId": 4335467.0,
      "addressId": 0,
      "polygonId": "18221-436",
      "neighborhoodName": "מורד הנחל",
      "neighborhoodId": 65210465,
      "address": "0",
      "dealDate": "2025-03-26",
      "dealAmount": 1180000,
      "parcelNum": "18221-436-2",
      "dealNature": "דירה בבית קומות",
      "roomNum": 4.0,
      "floor": "ראשונה",
      "assetArea": 115.0,
      "yearBuilt": 0,
      "streetCode": 0,
      "settlmentID": 812,
      "buildingFloors": 0,
      "hokHamecher": 0,
      "trend": {
        "rate": 0,
        "years": 0
      },
      "prevDeals": [],
      "ownership": [],
      "priceSM": 10261,
      "row_id": 2
    },
    {
      "assetId": 4335463.0,
      "addressId": 0,
      "polygonId": "18221-438",
      "neighborhoodName": "מורד הנחל",
      "neighborhoodId": 65210465,
      "address": "0",
      "dealDate": "2025-03-06",
      "dealAmount": 1225000,
      "parcelNum": "18221-438-4",
      "dealNature": "דירה בבית קומות",
      "roomNum": 4.0,
      "floor": null,
      "assetArea": 120.0,
      "yearBuilt": 0,
      "streetCode": 0,
      "settlmentID": 812,
      "buildingFloors": 0,
      "hokHamecher": 0,
      "trend": {
        "rate": 0,
        "years": 0
      },
      "prevDeals": [],
      "ownership": [],
      "priceSM": 10208,
      "row_id": 3
    },
    {
      "assetId": 4335479.0,
      "addressId": 0,
      "polygonId": "18221-437",
      "neighborhoodName": "מורד הנחל",
      "neighborhoodId": 65210465,
      "address": "0",
      "dealDate": "2024-12-29",
      "dealAmount": 1370000,
      "parcelNum": "18221-437-2",
      "dealNature": "דירה בבית קומות",
      "roomNum": 4.0,
      "floor": "שניה",
      "assetArea": 128.0,
      "yearBuilt": 0,
      "streetCode": 0,
      "settlmentID": 812,
      "buildingFloors": 0,
      "hokHamecher": 0,
      "trend": {
        "rate": 0,
        "years": 0
      },
      "prevDeals": [],
      "ownership": [],
      "priceSM": 10703,
      "row_id": 4
    },
    {
      "assetId": 4335478.0,
      "addressId": 0,
      "polygonId": "18221-438",
      "neighborhoodName": "מורד הנחל",
      "neighborhoodId": 65210465,
      "address": "0",
      "dealDate": "2024-07-11",
      "dealAmount": 1500000,
      "parcelNum": "18221-438-3",
      "dealNature": "דירה בבית קומות",
      "roomNum": 4.0,
      "floor": "ראשונה",
      "assetArea": 130.0,
      "yearBuilt": 0,
      "streetCode": 0,
      "settlmentID": 812,
      "buildingFloors": 0,
      "hokHamecher": 0,
      "trend": {
        "rate": 0,
        "years": 0
      },
      "prevDeals": [],
      "ownership": [],
      "priceSM": 11538,
      "row_id": 5
    },
    {
      "assetId": 4335477.0,
      "addressId": 0,
      "polygonId": "18221-438",
      "neighborhoodName": "מורד הנחל",
      "neighborhoodId": 65210465,
      "address": "0",
      "dealDate": "2024-06-02",
      "dealAmount": 1250000,
      "parcelNum": "18221-438-2",
      "dealNature": "דירה בבית קומות",
      "roomNum": 4.0,
      "floor": "ראשונה",
      "assetArea": 124.0,
      "yearBuilt": 0,
      "streetCode": 0,
      "settlmentID": 812,
      "buildingFloors": 0,
      "hokHamecher": 0,
      "trend": {
        "rate": 0,
        "years": 0
      },
      "prevDeals": [],
      "ownership": [],
      "priceSM": 10081,
      "row_id": 6
    },
    {
      "assetId": 4335381.0,
      "addressId": 0,
      "polygonId": "18221-34",
      "neighborhoodName": "מורד הנחל",
      "neighborhoodId": 65210465,
      "address": "0",
      "dealDate": "2022-12-18",
      "dealAmount": 1547000,
      "parcelNum": "18221-34-2",
      "dealNature": "דירה בבית קומות",
      "roomNum": 4.0,
      "floor": "ראשונה",
      "assetArea": 110.0,
      "yearBuilt": 0,
      "streetCode": 0,
      "settlmentID": 812,
      "buildingFloors": 0,
      "hokHamecher": 0,
      "trend": {
        "rate": 0,
        "years": 0
      },
      "prevDeals": [],
      "ownership": [],
      "priceSM": 14064,
      "row_id": 7
    },
    {
      "assetId": 4335206.0,
      "addressId": 0,
      "polygonId": "18221-437",
      "neighborhoodName": "מורד הנחל",
      "neighborhoodId": 65210465,
      "address": "0",
      "dealDate": "2022-12-11",
      "dealAmount": 1400000,
      "parcelNum": "18221-437-1",
      "dealNature": "דירה בבית קומות",
      "roomNum": 4.0,
      "floor": "ראשונה",
      "assetArea": 125.0,
      "yearBuilt": 0,
      "streetCode": 0,
      "settlmentID": 812,
      "buildingFloors": 0,
      "hokHamecher": 0,
      "trend": {
        "rate": 0,
        "years": 0
      },
      "prevDeals": [],
      "ownership": [],
      "priceSM": 11200,
      "row_id": 8
    },
    {
      "assetId": 4335381.0,
      "addressId": 0,
      "polygonId": "18221-34",
      "neighborhoodName": "מורד הנחל",
      "neighborhoodId": 65210465,
      "address": "0",
      "dealDate": "2022-08-02",
      "dealAmount": 1250000,
      "parcelNum": "18221-34-3",
      "dealNature": "דירה בבית קומות",
      "roomNum": 4.0,
      "floor": "ראשונה",
      "assetArea": 113.0,
      "yearBuilt": 0,
      "streetCode": 0,
      "settlmentID": 812,
      "buildingFloors": 0,
      "hokHamecher": 0,
      "trend": {
        "rate": 0,
        "years": 0
      },
      "prevDeals": [],
      "ownership": [],
      "priceSM": 11062,
      "row_id": 9
    },
    {
      "assetId": 4335462.0,
      "addressId": 0,
      "polygonId": "18221-438",
      "neighborhoodName": "מורד הנחל",
      "neighborhoodId": 65210465,
      "address": "0",
      "dealDate": "2021-06-02",
      "dealAmount": 1150000,
      "parcelNum": "18221-438-1",
      "dealNature": "דירה בבית קומות",
      "roomNum": 4.0,
      "floor": null,
      "assetArea": 100.0,
      "yearBuilt": 0,
      "streetCode": 0,
      "settlmentID": 812,
      "buildingFloors": 0,
      "hokHamecher": 0,
      "trend": {
        "rate": 0,
        "years": 0
      },
      "prevDeals": [],
      "ownership": [],
      "priceSM": 11500,
      "row_id": 10
    },
    {
      "assetId": 4335381.0,
      "addressId": 0,
      "polygonId": "18221-34",
      "neighborhoodName": "מורד הנחל",
      "neighborhoodId": 65210465,
      "address": "0",
      "dealDate": "2021-05-07",
      "dealAmount": 1075000,
      "parcelNum": "18221-34-4",
      "dealNature": "דירה בבית קומות",
      "roomNum": 4.0,
      "floor": "שלישית",
      "assetArea": 125.0,
      "yearBuilt": 0,
      "streetCode": 0,
      "settlmentID": 812,
      "buildingFloors": 0,
      "hokHamecher": 0,
      "trend": {
        "rate": 0,
        "years": 0
      },
      "prevDeals": [],
      "ownership": [],
      "priceSM": 8600,
      "row_id": 11
    },
    {
      "assetId": 4335381.0,
      "addressId": 0,
      "polygonId": "18221-34",
      "neighborhoodName": "מורד הנחל",
      "neighborhoodId": 65210465,
      "address": "0",
      "dealDate": "2021-03-08",
      "dealAmount": 1000000,
      "parcelNum": "18221-34-5",
      "dealNature": "דירה בבית קומות",
      "roomNum": 4.0,
      "floor": "ראשונה",
      "assetArea": 125.0,
      "yearBuilt": 0,
      "streetCode": 0,
      "settlmentID": 812,
      "buildingFloors": 0,
      "hokHamecher": 0,
      "trend": {
        "rate": 0,
        "years": 0
      },
      "prevDeals": [],
      "ownership": [],
      "priceSM": 8000,
      "row_id": 12
    },
    {
      "assetId": 4335479.0,
      "addressId": 0,
      "polygonId": "18221-437",
      "neighborhoodName": "מורד הנחל",
      "neighborhoodId": 65210465,
      "address": "0",
      "dealDate": "2020-10-28",
      "dealAmount": 1080000,
      "parcelNum": "18221-437-3",
      "dealNature": "דירה בבית קומות",
      "roomNum": 4.0,
      "floor": "ראשונה",
      "assetArea": 88.0,
      "yearBuilt": 0,
      "streetCode": 0,
      "settlmentID": 812,
      "buildingFloors": 0,
      "hokHamecher": 0,
      "trend": {
        "rate": 0,
        "years": 0
      },
      "prevDeals": [],
      "ownership": [],
      "priceSM": 12273,
      "row_id": 13
    },
    {
      "assetId": 4335381.0,
      "addressId": 0,
      "polygonId": "18221-34",
      "neighborhoodName": "מורד הנחל",
      "neighborhoodId": 65210465,
      "address": "0",
      "dealDate": "2020-06-30",
      "dealAmount": 1180000,
      "parcelNum": "18221-34-6",
      "dealNature": "דירה בבית קומות",
      "roomNum": 4.0,
      "floor": "ראשונה",
      "assetArea": 95.0,
      "yearBuilt": 0,
      "streetCode": 0,
      "settlmentID": 812,
      "buildingFloors": 0,
      "hokHamecher": 0,
      "trend": {
        "rate": 0,
        "years": 0
      },
      "prevDeals": [],
      "ownership": [],
      "priceSM": 12421,
      "row_id": 14
    },
    {
      "assetId": 4335381.0,
      "addressId": 0,
      "polygonId": "18221-34",
      "neighborhoodName": "מורד הנחל",
      "neighborhoodId": 65210465,
      "address": "0",
      "dealDate": "2020-04-30",
      "dealAmount": 1025000,
      "parcelNum": "18221-34-7",
      "dealNature": "דירה בבית קומות",
      "roomNum": 4.0,
      "floor": null,
      "assetArea": 110.0,
      "yearBuilt": 0,
      "streetCode": 0,
      "settlmentID": 812,
      "buildingFloors": 0,
      "hokHamecher": 0,
      "trend": {
        "rate": 0,
        "years": 0
      },
      "prevDeals": [],
      "ownership": [],
      "priceSM": 9318,
      "row_id": 15
    },
    {
      "assetId": 4335381.0,
      "addressId": 0,
      "polygonId": "18221-34",
      "neighborhoodName": "מורד הנחל",
      "neighborhoodId": 65210465,
      "address": "0",
      "dealDate": "2019-12-31",
      "dealAmount": 1025000,
      "parcelNum": "18221-34-8",
      "dealNature": "דירה בבית קומות",
      "roomNum": 4.0,
      "floor": null,
      "assetArea": 120.0,
      "yearBuilt": 0,
      "streetCode": 0,
      "settlmentID": 812,
      "buildingFloors": 0,
      "hokHamecher": 0,
      "trend": {
        "rate": 0,
        "years": 0
      },
      "prevDeals": [],
      "ownership": [],
      "priceSM": 8542,
      "row_id": 16
    },
    {
      "assetId": 4335381.0,
      "addressId": 0,
      "polygonId": "18221-34",
      "neighborhoodName": "מורד הנחל",
      "neighborhoodId": 65210465,
      "address": "0",
      "dealDate": "2019-12-25",
      "dealAmount": 1000000,
      "parcelNum": "18221-34-9",
      "dealNature": "דירה בבית קומות",
      "roomNum": 4.0,
      "floor": null,
      "assetArea": 87.0,
      "yearBuilt": 0,
      "streetCode": 0,
      "settlmentID": 812,
      "buildingFloors": 0,
      "hokHamecher": 0,
      "trend": {
        "rate": 0,
        "years": 0
      },
      "prevDeals": [],
      "ownership": [],
      "priceSM": 11494,
      "row_id": 17
    },
    {
      "assetId": 4335381.0,
      "addressId": 0,
      "polygonId": "18221-34",
      "neighborhoodName": "מורד הנחל",
      "neighborhoodId": 65210465,
      "address": "0",
      "dealDate": "2019-04-18",
      "dealAmount": 1040000,
      "parcelNum": "18221-34-11",
      "dealNature": "דירה בבית קומות",
      "roomNum": 4.0,
      "floor": "שניה",
      "assetArea": 125.0,
      "yearBuilt": 0,
      "streetCode": 0,
      "settlmentID": 812,
      "buildingFloors": 0,
      "hokHamecher": 0,
      "trend": {
        "rate": 0,
        "years": 0
      },
      "prevDeals": [],
      "ownership": [],
      "priceSM": 8320,
      "row_id": 18
    },
    {
      "assetId": 4335381.0,
      "addressId": 0,
      "polygonId": "18221-34",
      "neighborhoodName": "מורד הנחל",
      "neighborhoodId": 65210465,
      "address": "0",
      "dealDate": "2018-08-19",
      "dealAmount": 950000,
      "parcelNum": "18221-34-13",
      "dealNature": "דירה בבית קומות",
      "roomNum": 4.0,
      "floor": null,
      "assetArea": 130.0,
      "yearBuilt": 0,
      "streetCode": 0,
      "settlmentID": 812,
      "buildingFloors": 0,
      "hokHamecher": 0,
      "trend": {
        "rate": 0,
        "years": 0
      },
      "prevDeals": [],
      "ownership": [],
      "priceSM": 7308,
      "row_id": 19
    },
    {
      "assetId": 4335381.0,
      "addressId": 0,
      "polygonId": "18221-34",
      "neighborhoodName": "מורד הנחל",
      "neighborhoodId": 65210465,
      "address": "0",
      "dealDate": "2015-11-03",
      "dealAmount": 695000,
      "parcelNum": "18221-34-16",
      "dealNature": "דירה בבית קומות",
      "roomNum": 3.0,
      "floor": "ראשונה",
      "assetArea": 77.0,
      "yearBuilt": 0,
      "streetCode": 0,
      "settlmentID": 812,
      "buildingFloors": 0,
      "hokHamecher": 0,
      "trend": {
        "rate": 0,
        "years": 0
      },
      "prevDeals": [],
      "ownership": [],
      "priceSM": 9026,
      "row_id": 20
    },
    {
      "assetId": 4335381.0,
      "addressId": 0,
      "polygonId": "18221-34",
      "neighborhoodName": "מורד הנחל",
      "neighborhoodId": 65210465,
      "address": "0",
      "dealDate": "2015-01-20",
      "dealAmount": 926000,
      "parcelNum": "18221-34-17",
      "dealNature": "דירה בבית קומות",
      "roomNum": 5.0,
      "floor": "רביעית",
      "assetArea": 100.0,
      "yearBuilt": 0,
      "streetCode": 0,
      "settlmentID": 812,
      "buildingFloors": 0,
      "hokHamecher": 0,
      "trend": {
        "rate": 0,
        "years": 0
      },
      "prevDeals": [],
      "ownership": [],
      "priceSM": 9260,
      "row_id": 21
    },
    {
      "assetId": 4335381.0,
      "addressId": 0,
      "polygonId": "18221-34",
      "neighborhoodName": "מורד הנחל",
      "neighborhoodId": 65210465,
      "address": "0",
      "dealDate": "2014-11-06",
      "dealAmount": 819000,
      "parcelNum": "18221-34-18",
      "dealNature": "דירה בבית קומות",
      "roomNum": 4.0,
      "floor": null,
      "assetArea": 98.0,
      "yearBuilt": 0,
      "streetCode": 0,
      "settlmentID": 812,
      "buildingFloors": 0,
      "hokHamecher": 0,
      "trend": {
        "rate": 0,
        "years": 0
      },
      "prevDeals": [],
      "ownership": [],
      "priceSM": 8357,
      "row_id": 22
    },
    {
      "assetId": 4335381.0,
      "addressId": 0,
      "polygonId": "18221-34",
      "neighborhoodName": "מורד הנחל",
      "neighborhoodId": 65210465,
      "address": "0",
      "dealDate": "2013-01-31",
      "dealAmount": 640000,
      "parcelNum": "18221-34-19",
      "dealNature": "דירה בבית קומות",
      "roomNum": 3.0,
      "floor": null,
      "assetArea": 86.0,
      "yearBuilt": 0,
      "streetCode": 0,
      "settlmentID": 812,
      "buildingFloors": 0,
      "hokHamecher": 0,
      "trend": {
        "rate": 0,
        "years": 0
      },
      "prevDeals": [],
      "ownership": [],
      "priceSM": 7442,
      "row_id": 23
    },
    {
      "assetId": 4335381.0,
      "addressId": 0,
      "polygonId": "18221-34",
      "neighborhoodName": "מורד הנחל",
      "neighborhoodId": 65210465,
      "address": "0",
      "dealDate": "2013-01-13",
      "dealAmount": 671000,
      "parcelNum": "18221-34-20",
      "dealNature": "דירה בבית קומות",
      "roomNum": 4.0,
      "floor": "חמישית",
      "assetArea": 94.0,
      "yearBuilt": 0,
      "streetCode": 0,
      "settlmentID": 812,
      "buildingFloors": 0,
      "hokHamecher": 0,
      "trend": {
        "rate": 0,
        "years": 0
      },
      "prevDeals": [],
      "ownership": [],
      "priceSM": 7138,
      "row_id": 24
    },
    {
      "assetId": 4335381.0,
      "addressId": 0,
      "polygonId": "18221-34",
      "neighborhoodName": "מורד הנחל",
      "neighborhoodId": 65210465,
      "address": "0",
      "dealDate": "2012-12-16",
      "dealAmount": 770000,
      "parcelNum": "18221-34-21",
      "dealNature": "דירה בבית קומות",
      "roomNum": 4.0,
      "floor": "שניה",
      "assetArea": 92.0,
      "yearBuilt": 0,
      "streetCode": 0,
      "settlmentID": 812,
      "buildingFloors": 0,
      "hokHamecher": 0,
      "trend": {
        "rate": 0,
        "years": 0
      },
      "prevDeals": [],
      "ownership": [],
      "priceSM": 8370,
      "row_id": 25
    },
    {
      "assetId": 4335381.0,
      "addressId": 0,
      "polygonId": "18221-34",
      "neighborhoodName": "מורד הנחל",
      "neighborhoodId": 65210465,
      "address": "0",
      "dealDate": "2012-12-03",
      "dealAmount": 748000,
      "parcelNum": "18221-34-22",
      "dealNature": "דירה בבית קומות",
      "roomNum": 4.0,
      "floor": null,
      "assetArea": 90.0,
      "yearBuilt": 0,
      "streetCode": 0,
      "settlmentID": 812,
      "buildingFloors": 0,
      "hokHamecher": 0,
      "trend": {
        "rate": 0,
        "years": 0
      },
      "prevDeals": [],
      "ownership": [],
      "priceSM": 8311,
      "row_id": 26
    },
    {
      "assetId": 4335381.0,
      "addressId": 0,
      "polygonId": "18221-34",
      "neighborhoodName": "מורד הנחל",
      "neighborhoodId": 65210465,
      "address": "0",
      "dealDate": "2011-05-22",
      "dealAmount": 530000,
      "parcelNum": "18221-34-23",
      "dealNature": "דירה בבית קומות",
      "roomNum": 3.0,
      "floor": "ראשונה",
      "assetArea": 70.0,
      "yearBuilt": 0,
      "streetCode": 0,
      "settlmentID": 812,
      "buildingFloors": 0,
      "hokHamecher": 0,
      "trend": {
        "rate": 0,
        "years": 0
      },
      "prevDeals": [],
      "ownership": [],
      "priceSM": 7571,
      "row_id": 27
    },
    {
      "assetId": 4335381.0,
      "addressId": 0,
      "polygonId": "18221-34",
      "neighborhoodName": "מורד הנחל",
      "neighborhoodId": 65210465,
      "address": "0",
      "dealDate": "2010-09-14",
      "dealAmount": 610000,
      "parcelNum": "18221-34-24",
      "dealNature": "דירה בבית קומות",
      "roomNum": 5.0,
      "floor": null,
      "assetArea": 133.0,
      "yearBuilt": 0,
      "streetCode": 0,
      "settlmentID": 812,
      "buildingFloors": 0,
      "hokHamecher": 0,
      "trend": {
        "rate": 0,
        "years": 0
      },
      "prevDeals": [],
      "ownership": [],
      "priceSM": 4586,
      "row_id": 28
    },
    {
      "assetId": 4335381.0,
      "addressId": 0,
      "polygonId": "18221-34",
      "neighborhoodName": "מורד הנחל",
      "neighborhoodId": 65210465,
      "address": "0",
      "dealDate": "2010-08-01",
      "dealAmount": 690000,
      "parcelNum": "18221-34-25",
      "dealNature": "דירה בבית קומות",
      "roomNum": 5.0,
      "floor": "רביעית",
      "assetArea": 110.0,
      "yearBuilt": 0,
      "streetCode": 0,
      "settlmentID": 812,
      "buildingFloors": 0,
      "hokHamecher": 0,
      "trend": {
        "rate": 0,
        "years": 0
      },
      "prevDeals": [],
      "ownership": [],
      "priceSM": 6273,
      "row_id": 29
    },
    {
      "assetId": 4335381.0,
      "addressId": 0,
      "polygonId": "18221-34",
      "neighborhoodName": "מורד הנחל",
      "neighborhoodId": 65210465,
      "address": "0",
      "dealDate": "2010-02-01",
      "dealAmount": 640000,
      "parcelNum": "18221-34-26",
      "dealNature": "דירה בבית קומות",
      "roomNum": 4.0,
      "floor": null,
      "assetArea": 92.0,
      "yearBuilt": 0,
      "streetCode": 0,
      "settlmentID": 812,
      "buildingFloors": 0,
      "hokHamecher": 0,
      "trend": {
        "rate": 0,
        "years": 0
      },
      "prevDeals": [],
      "ownership": [],
      "priceSM": 6957,
      "row_id": 30
    },
    {
      "assetId": 4335381.0,
      "addressId": 0,
      "polygonId": "18221-34",
      "neighborhoodName": "מורד הנחל",
      "neighborhoodId": 65210465,
      "address": "0",
      "dealDate": "2009-06-07",
      "dealAmount": 480000,
      "parcelNum": "18221-34-27",
      "dealNature": "דירה בבית קומות",
      "roomNum": 4.0,
      "floor": "ראשונה",
      "assetArea": 130.0,
      "yearBuilt": 0,
      "streetCode": 0,
      "settlmentID": 812,
      "buildingFloors": 0,
      "hokHamecher": 0,
      "trend": {
        "rate": 0,
        "years": 0
      },
      "prevDeals": [],
      "ownership": [],
      "priceSM": 3692,
      "row_id": 31
    },
    {
      "assetId": 4335381.0,
      "addressId": 0,
      "polygonId": "18221-34",
      "neighborhoodName": "מורד הנחל",
      "neighborhoodId": 65210465,
      "address": "0",
      "dealDate": "2009-05-12",
      "dealAmount": 610000,
      "parcelNum": "18221-34-28",
      "dealNature": "דירה בבית קומות",
      "roomNum": 5.0,
      "floor": null,
      "assetArea": 106.0,
      "yearBuilt": 0,
      "streetCode": 0,
      "settlmentID": 812,
      "buildingFloors": 0,
      "hokHamecher": 0,
      "trend": {
        "rate": 0,
        "years": 0
      },
      "prevDeals": [],
      "ownership": [],
      "priceSM": 5755,
      "row_id": 32
    },
    {
      "assetId": 4335381.0,
      "addressId": 0,
      "polygonId": "18221-34",
      "neighborhoodName": "מורד הנחל",
      "neighborhoodId": 65210465,
      "address": "0",
      "dealDate": "2008-04-06",
      "dealAmount": 365000,
      "parcelNum": "18221-34-29",
      "dealNature": "דירה בבית קומות",
      "roomNum": 4.0,
      "floor": null,
      "assetArea": 110.0,
      "yearBuilt": 0,
      "streetCode": 0,
      "settlmentID": 812,
      "buildingFloors": 0,
      "hokHamecher": 0,
      "trend": {
        "rate": 0,
        "years": 0
      },
      "prevDeals": [],
      "ownership": [],
      "priceSM": 3318,
      "row_id": 33
    },
    {
      "assetId": 4335381.0,
      "addressId": 0,
      "polygonId": "18221-34",
      "neighborhoodName": "מורד הנחל",
      "neighborhoodId": 65210465,
      "address": "0",
      "dealDate": "2006-10-29",
      "dealAmount": 385000,
      "parcelNum": "18221-34-30",
      "dealNature": "דירה בבית קומות",
      "roomNum": 4.0,
      "floor": null,
      "assetArea": 100.0,
      "yearBuilt": 0,
      "streetCode": 0,
      "settlmentID": 812,
      "buildingFloors": 0,
      "hokHamecher": 0,
      "trend": {
        "rate": 0,
        "years": 0
      },
      "prevDeals": [],
      "ownership": [],
      "priceSM": 3850,
      "row_id": 34
    },
    {
      "assetId": 4335381.0,
      "addressId": 0,
      "polygonId": "18221-34",
      "neighborhoodName": "מורד הנחל",
      "neighborhoodId": 65210465,
      "address": "0",
      "dealDate": "2006-07-04",
      "dealAmount": 600000,
      "parcelNum": "18221-34-31",
      "dealNature": "דירה בבית קומות",
      "roomNum": 5.0,
      "floor": null,
      "assetArea": 120.0,
      "yearBuilt": 0,
      "streetCode": 0,
      "settlmentID": 812,
      "buildingFloors": 0,
      "hokHamecher": 0,
      "trend": {
        "rate": 0,
        "years": 0
      },
      "prevDeals": [],
      "ownership": [],
      "priceSM": 5000,
      "row_id": 35
    },
    {
      "assetId": 4335381.0,
      "addressId": 0,
      "polygonId": "18221-34",
      "neighborhoodName": "מורד הנחל",
      "neighborhoodId": 65210465,
      "address": "0",
      "dealDate": "2005-11-15",
      "dealAmount": 469000,
      "parcelNum": "18221-34-32",
      "dealNature": "דירה בבית קומות",
      "roomNum": 5.0,
      "floor": null,
      "assetArea": 120.0,
      "yearBuilt": 0,
      "streetCode": 0,
      "settlmentID": 812,
      "buildingFloors": 0,
      "hokHamecher": 0,
      "trend": {
        "rate": 0,
        "years": 0
      },
      "prevDeals": [],
      "ownership": [],
      "priceSM": 3908,
      "row_id": 36
    },
    {
      "assetId": 4335381.0,
      "addressId": 0,
      "polygonId": "18221-34",
      "neighborhoodName": "מורד הנחל",
      "neighborhoodId": 65210465,
      "address": "0",
      "dealDate": "2004-08-06",
      "dealAmount": 448000,
      "parcelNum": "18221-34-33",
      "dealNature": "דירה בבית קומות",
      "roomNum": 4.0,
      "floor": null,
      "assetArea": 100.0,
      "yearBuilt": 0,
      "streetCode": 0,
      "settlmentID": 812,
      "buildingFloors": 0,
      "hokHamecher": 0,
      "trend": {
        "rate": 0,
        "years": 0
      },
      "prevDeals": [],
      "ownership": [],
      "priceSM": 4480,
      "row_id": 37
    }
  ]
}