{
  "neighborhood_name": "מרכז העיר מזרח",
  "city_name": "ירושלים",
  "transaction_count": 55,
  "transactions": [
    {
      "assetId": 4227889.0,
      "addressId": 0,
      "polygonId": "30092-32",
      "neighborhoodName": "מרכז העיר מזרח",
      "neighborhoodId": 65209838,
      "address": "0",
      "dealDate": "2025-07-03",
      "dealAmount": 2800000,
      "parcelNum": "30092-32-4",
      "dealNature": "דירה בבית קומות",
      "roomNum": 3.0,
      "floor": null,
      "assetArea": 82.0,
      "yearBuilt": 0,
      "streetCode": 0,
      "settlmentID": 3000,
      "buildingFloors": 0,
      "hokHamecher": 0,
      "trend": {
        "rate": 0,
        "years": 0
      },
      "prevDeals": [],
      "ownership": [],
      "priceSM": 34146,
      "row_id": 1
    },
    {
      "assetId": 4227883.0,
      "addressId": 0,
      "polygonId": "30092-31",
      "neighborhoodName": "מרכז העיר מזרח",
      "neighborhoodId": 65209838,
      "address": "0",
      "dealDate": "2025-05-26",
      "dealAmount": 2989000,
      "parcelNum": "30092-31-19",
      "dealNature": "דירה בבית קומות",
      "roomNum": 3.0,
      "floor": "תשע עשרה",
      "assetArea": 82.0,
      "yearBuilt": 0,
      "streetCode": 0,
      "settlmentID": 3000,
      "buildingFloors": 0,
      "hokHamecher": 0,
      "prevDeals": [
        {
          "dealDate": "2025-05-26",
          "dealAmount": 2959000
        }
      ],
      "trend": {
        "rate": 1.0,
        "years": 0.0
      },
      "ownership": [],
      "priceSM": 36451,
      "row_id": 2
    },
    {
      "assetId": 4227889.0,
      "addressId": 0,
      "polygonId": "30092-32",
      "neighborhoodName": "מרכז העיר מזרח",
      "neighborhoodId": 65209838,
      "address": "0",
      "dealDate": "2025-05-15",
      "dealAmount": 3826000,
      "parcelNum": "30092-32-5",
      "dealNature": "דירה בבית קומות",
      "roomNum": 4.0,
      "floor": "שלוש עשרה",
      "assetArea": 96.0,
      "yearBuilt": 0,
      "streetCode": 0,
      "settlmentID": 3000,
      "buildingFloors": 0,
      "hokHamecher": 0,
      "trend": {
        "rate": 0,
        "years": 0
      },
      "prevDeals": [],
      "ownership": [],
      "priceSM": 39854,
      "row_id": 3
    },
    {
      "assetId": 4227883.0,
      "addressId": 0,
      "polygonId": "30092-31",
      "neighborhoodName": "מרכז העיר מזרח",
      "neighborhoodId": 65209838,
      "address": "0",
      "dealDate": "2025-03-20",
      "dealAmount": 3305000,
      "parcelNum": "30092-31-21",
      "dealNature": "דירה בבית קומות",
      "roomNum": 3.0,
      "floor": "עשרים ושלוש",
      "assetArea": 96.0,
      "yearBuilt": 0,
      "streetCode": 0,
      "settlmentID": 3000,
      "buildingFloors": 0,
      "hokHamecher": 0,
      "prevDeals": [
        {
          "dealDate": "2025-03-20",
          "dealAmount": 3375000
        }
      ],
      "trend": {
        "rate": -2.1,
        "years": 0.0
      },
      "ownership": [],
      "priceSM": 34427,
      "row_id": 4
    },
    {
      "assetId": 4227883.0,
      "addressId": 0,
      "polygonId": "30092-31",
      "neighborhoodName": "מרכז העיר מזרח",
      "neighborhoodId": 65209838,
      "address": "0",
      "dealDate": "2025-01-26",
      "dealAmount": 4086000,
      "parcelNum": "30092-31-23",
      "dealNature": "דירה בבית קומות",
      "roomNum": 4.0,
      "floor": "עשרים ותשע",
      "assetArea": 96.0,
      "yearBuilt": 0,
      "streetCode": 0,
      "settlmentID": 3000,
      "buildingFloors": 0,
      "hokHamecher": 0,
      "trend": {
        "rate": 0,
        "years": 0
      },
      "prevDeals": [],
      "ownership": [],
      "priceSM": 42562,
      "row_id": 5
    },
    {
      "assetId": 4227883.0,
      "addressId": 0,
      "polygonId": "30092-31",
      "neighborhoodName": "מרכז העיר מזרח",
      "neighborhoodId": 65209838,
      "address": "0",
      "dealDate": "2024-12-31",
      "dealAmount": 6370000,
      "parcelNum": "30092-31-24",
      "dealNature": "דירה בבית קומות",
      "roomNum": 4.0,
      "floor": "ראשונה",
      "assetArea": 107.0,
      "yearBuilt": 0,
      "streetCode": 0,
      "settlmentID": 3000,
      "buildingFloors": 0,
      "hokHamecher": 0,
      "trend": {
        "rate": 0,
        "years": 0
      },
      "prevDeals": [],
      "ownership": [],
      "priceSM": 59533,
      "row_id": 7
    },
    {
      "assetId": 4227883.0,
      "addressId": 0,
      "polygonId": "30092-31",
      "neighborhoodName": "מרכז העיר מזרח",
      "neighborhoodId": 65209838,
      "address": "0",
      "dealDate": "2024-12-30",
      "dealAmount": 3307000,
      "parcelNum": "30092-31-25",
      "dealNature": "דירה בבית קומות",
      "roomNum": 3.0,
      "floor": "עשרים ותשע",
      "assetArea": 82.0,
      "yearBuilt": 0,
      "streetCode": 0,
      "settlmentID": 3000,
      "buildingFloors": 0,
      "hokHamecher": 0,
      "prevDeals": [
        {
          "dealDate": "2024-12-30",
          "dealAmount": 4699000
        },
        {
          "dealDate": "2024-12-30",
          "dealAmount": 3487000
        },
        {
          "dealDate": "2024-12-30",
          "dealAmount": 3157000
        },
        {
          "dealDate": "2024-12-30",
          "dealAmount": 3517000
        },
        {
          "dealDate": "2024-12-30",
          "dealAmount": 3143000
        },
        {
          "dealDate": "2024-12-30",
          "dealAmount": 4022000
        }
      ],
      "trend": {
        "rate": -29.6,
        "years": 0.0
      },
      "ownership": [],
      "priceSM": 40329,
      "row_id": 8
    },
    {
      "assetId": 4227889.0,
      "addressId": 0,
      "polygonId": "30092-32",
      "neighborhoodName": "מרכז העיר מזרח",
      "neighborhoodId": 65209838,
      "address": "0",
      "dealDate": "2024-12-17",
      "dealAmount": 3606000,
      "parcelNum": "30092-32-6",
      "dealNature": "דירה בבית קומות",
      "roomNum": 4.0,
      "floor": "חמש עשרה",
      "assetArea": 96.0,
      "yearBuilt": 0,
      "streetCode": 0,
      "settlmentID": 3000,
      "buildingFloors": 0,
      "hokHamecher": 0,
      "trend": {
        "rate": 0,
        "years": 0
      },
      "prevDeals": [],
      "ownership": [],
      "priceSM": 37562,
      "row_id": 9
    },
    {
      "assetId": 4227889.0,
      "addressId": 0,
      "polygonId": "30092-32",
      "neighborhoodName": "מרכז העיר מזרח",
      "neighborhoodId": 65209838,
      "address": "0",
      "dealDate": "2024-12-12",
      "dealAmount": 3616000,
      "parcelNum": "30092-32-7",
      "dealNature": "דירה בבית קומות",
      "roomNum": 4.0,
      "floor": "שש עשרה",
      "assetArea": 96.0,
      "yearBuilt": 0,
      "streetCode": 0,
      "settlmentID": 3000,
      "buildingFloors": 0,
      "hokHamecher": 0,
      "trend": {
        "rate": 0,
        "years": 0
      },
      "prevDeals": [],
      "ownership": [],
      "priceSM": 37667,
      "row_id": 10
    },
    {
      "assetId": 4227883.0,
      "addressId": 0,
      "polygonId": "30092-31",
      "neighborhoodName": "מרכז העיר מזרח",
      "neighborhoodId": 65209838,
      "address": "0",
      "dealDate": "2024-12-03",
      "dealAmount": 3908000,
      "parcelNum": "30092-31-32",
      "dealNature": "דירה בבית קומות",
      "roomNum": 4.0,
      "floor": "עשרים וארבע",
      "assetArea": 95.0,
      "yearBuilt": 0,
      "streetCode": 0,
      "settlmentID": 3000,
      "buildingFloors": 0,
      "hokHamecher": 0,
      "trend": {
        "rate": 0,
        "years": 0
      },
      "prevDeals": [],
      "ownership": [],
      "priceSM": 41137,
      "row_id": 11
    },
    {
      "assetId": 4227883.0,
      "addressId": 0,
      "polygonId": "30092-31",
      "neighborhoodName": "מרכז העיר מזרח",
      "neighborhoodId": 65209838,
      "address": "0",
      "dealDate": "2024-08-26",
      "dealAmount": 4009000,
      "parcelNum": "30092-31-33",
      "dealNature": "דירה בבית קומות",
      "roomNum": 5.0,
      "floor": "עשרים",
      "assetArea": 123.0,
      "yearBuilt": 0,
      "streetCode": 0,
      "settlmentID": 3000,
      "buildingFloors": 0,
      "hokHamecher": 0,
      "trend": {
        "rate": 0,
        "years": 0
      },
      "prevDeals": [],
      "ownership": [],
      "priceSM": 32593,
      "row_id": 13
    },
    {
      "assetId": 4227883.0,
      "addressId": 0,
      "polygonId": "30092-31",
      "neighborhoodName": "מרכז העיר מזרח",
      "neighborhoodId": 65209838,
      "address": "0",
      "dealDate": "2024-08-20",
      "dealAmount": 3353000,
      "parcelNum": "30092-31-34",
      "dealNature": "דירה בבית קומות",
      "roomNum": 4.0,
      "floor": "עשרים ושלוש",
      "assetArea": 95.0,
      "yearBuilt": 0,
      "streetCode": 0,
      "settlmentID": 3000,
      "buildingFloors": 0,
      "hokHamecher": 0,
      "trend": {
        "rate": 0,
        "years": 0
      },
      "prevDeals": [],
      "ownership": [],
      "priceSM": 35295,
      "row_id": 14
    },
    {
      "assetId": 4227883.0,
      "addressId": 0,
      "polygonId": "30092-31",
      "neighborhoodName": "מרכז העיר מזרח",
      "neighborhoodId": 65209838,
      "address": "0",
      "dealDate": "2024-08-04",
      "dealAmount": 3752000,
      "parcelNum": "30092-31-35",
      "dealNature": "דירה בבית קומות",
      "roomNum": 4.0,
      "floor": "תשע עשרה",
      "assetArea": 96.0,
      "yearBuilt": 0,
      "streetCode": 0,
      "settlmentID": 3000,
      "buildingFloors": 0,
      "hokHamecher": 0,
      "trend": {
        "rate": 0,
        "years": 0
      },
      "prevDeals": [],
      "ownership": [],
      "priceSM": 39083,
      "row_id": 15
    },
    {
      "assetId": 4227883.0,
      "addressId": 0,
      "polygonId": "30092-31",
      "neighborhoodName": "מרכז העיר מזרח",
      "neighborhoodId": 65209838,
      "address": "0",
      "dealDate": "2024-07-22",
      "dealAmount": 3623000,
      "parcelNum": "30092-31-36",
      "dealNature": "דירה בבית קומות",
      "roomNum": 4.0,
      "floor": "עשרים וחמש",
      "assetArea": 95.0,
      "yearBuilt": 0,
      "streetCode": 0,
      "settlmentID": 3000,
      "buildingFloors": 0,
      "hokHamecher": 0,
      "trend": {
        "rate": 0,
        "years": 0
      },
      "prevDeals": [],
      "ownership": [],
      "priceSM": 38137,
      "row_id": 16
    },
    {
      "assetId": 4227883.0,
      "addressId": 0,
      "polygonId": "30092-31",
      "neighborhoodName": "מרכז העיר מזרח",
      "neighborhoodId": 65209838,
      "address": "0",
      "dealDate": "2024-07-17",
      "dealAmount": 4700000,
      "parcelNum": "30092-31-37",
      "dealNature": "דירה בבית קומות",
      "roomNum": 5.0,
      "floor": "עשרים ושש",
      "assetArea": 123.0,
      "yearBuilt": 0,
      "streetCode": 0,
      "settlmentID": 3000,
      "buildingFloors": 0,
      "hokHamecher": 0,
      "trend": {
        "rate": 0,
        "years": 0
      },
      "prevDeals": [],
      "ownership": [],
      "priceSM": 38211,
      "row_id": 17
    },
    {
      "assetId": 4227883.0,
      "addressId": 0,
      "polygonId": "30092-31",
      "neighborhoodName": "מרכז העיר מזרח",
      "neighborhoodId": 65209838,
      "address": "0",
      "dealDate": "2024-06-26",
      "dealAmount": 2956000,
      "parcelNum": "30092-31-38",
      "dealNature": "דירה בבית קומות",
      "roomNum": 3.0,
      "floor": "ארבע עשרה",
      "assetArea": 81.0,
      "yearBuilt": 0,
      "streetCode": 0,
      "settlmentID": 3000,
      "buildingFloors": 0,
      "hokHamecher": 0,
      "trend": {
        "rate": 0,
        "years": 0
      },
      "prevDeals": [],
      "ownership": [],
      "priceSM": 36494,
      "row_id": 18
    },
    {
      "assetId": 4227883.0,
      "addressId": 0,
      "polygonId": "30092-31",
      "neighborhoodName": "מרכז העיר מזרח",
      "neighborhoodId": 65209838,
      "address": "0",
      "dealDate": "2024-06-19",
      "dealAmount": 3592000,
      "parcelNum": "30092-31-39",
      "dealNature": "דירה בבית קומות",
      "roomNum": 4.0,
      "floor": "עשרים וארבע",
      "assetArea": 95.0,
      "yearBuilt": 0,
      "streetCode": 0,
      "settlmentID": 3000,
      "buildingFloors": 0,
      "hokHamecher": 0,
      "trend": {
        "rate": 0,
        "years": 0
      },
      "prevDeals": [],
      "ownership": [],
      "priceSM": 37811,
      "row_id": 19
    },
    {
      "assetId": 4227883.0,
      "addressId": 0,
      "polygonId": "30092-31",
      "neighborhoodName": "מרכז העיר מזרח",
      "neighborhoodId": 65209838,
      "address": "0",
      "dealDate": "2024-06-09",
      "dealAmount": 3496000,
      "parcelNum": "30092-31-40",
      "dealNature": "דירה בבית קומות",
      "roomNum": 4.0,
      "floor": "עשרים ושתיים",
      "assetArea": 95.0,
      "yearBuilt": 0,
      "streetCode": 0,
      "settlmentID": 3000,
      "buildingFloors": 0,
      "hokHamecher": 0,
      "trend": {
        "rate": 0,
        "years": 0
      },
      "prevDeals": [],
      "ownership": [],
      "priceSM": 36800,
      "row_id": 20
    },
    {
      "assetId": 4227883.0,
      "addressId": 0,
      "polygonId": "30092-31",
      "neighborhoodName": "מרכז העיר מזרח",
      "neighborhoodId": 65209838,
      "address": "0",
      "dealDate": "2024-05-23",
      "dealAmount": 3340000,
      "parcelNum": "30092-31-41",
      "dealNature": "דירה בבית קומות",
      "roomNum": 4.0,
      "floor": "שש עשרה",
      "assetArea": 96.0,
      "yearBuilt": 0,
      "streetCode": 0,
      "settlmentID": 3000,
      "buildingFloors": 0,
      "hokHamecher": 0,
      "prevDeals": [
        {
          "dealDate": "2024-05-23",
          "dealAmount": 3403000
        }
      ],
      "trend": {
        "rate": -1.9,
        "years": 0.0
      },
      "ownership": [],
      "priceSM": 34792,
      "row_id": 21
    },
    {
      "assetId": 4227883.0,
      "addressId": 0,
      "polygonId": "30092-31",
      "neighborhoodName": "מרכז העיר מזרח",
      "neighborhoodId": 65209838,
      "address": "0",
      "dealDate": "2024-05-22",
      "dealAmount": 3434000,
      "parcelNum": "30092-31-44",
      "dealNature": "דירה בבית קומות",
      "roomNum": 4.0,
      "floor": "תשע עשרה",
      "assetArea": 95.0,
      "yearBuilt": 0,
      "streetCode": 0,
      "settlmentID": 3000,
      "buildingFloors": 0,
      "hokHamecher": 0,
      "trend": {
        "rate": 0,
        "years": 0
      },
      "prevDeals": [],
      "ownership": [],
      "priceSM": 36147,
      "row_id": 22
    },
    {
      "assetId": 4471872.0,
      "addressId": 66109879,
      "polygonId": "52651489",
      "neighborhoodName": "מרכז העיר מזרח",
      "neighborhoodId": 65209838,
      "address": "דלמן 7",
      "dealDate": "2024-05-20",
      "dealAmount": 754000,
      "parcelNum": "30821-11-1",
      "dealNature": "דירה בבית קומות",
      "roomNum": 2.0,
      "floor": "ראשונה",
      "assetArea": 35.0,
      "yearBuilt": 1940,
      "streetCode": 30000211,
      "settlmentID": 3000,
      "buildingFloors": 1,
      "hokHamecher": 0,
      "trend": {
        "rate": 0,
        "years": 0
      },
      "prevDeals": [],
      "ownership": [],
      "priceSM": 21543,
      "row_id": 23
    },
    {
      "assetId": 4227883.0,
      "addressId": 0,
      "polygonId": "30092-31",
      "neighborhoodName": "מרכז העיר מזרח",
      "neighborhoodId": 65209838,
      "address": "0",
      "dealDate": "2024-05-20",
      "dealAmount": 3496000,
      "parcelNum": "30092-31-45",
      "dealNature": "דירה בבית קומות",
      "roomNum": 4.0,
      "floor": "עשרים ואחת",
      "assetArea": 95.0,
      "yearBuilt": 0,
      "streetCode": 0,
      "settlmentID": 3000,
      "buildingFloors": 0,
      "hokHamecher": 0,
      "trend": {
        "rate": 0,
        "years": 0
      },
      "prevDeals": [],
      "ownership": [],
      "priceSM": 36800,
      "row_id": 24
    },
    {
      "assetId": 4227883.0,
      "addressId": 0,
      "polygonId": "30092-31",
      "neighborhoodName": "מרכז העיר מזרח",
      "neighborhoodId": 65209838,
      "address": "0",
      "dealDate": "2024-03-04",
      "dealAmount": 3628000,
      "parcelNum": "30092-31-46",
      "dealNature": "דירה בבית קומות",
      "roomNum": 5.0,
      "floor": "ארבע עשרה",
      "assetArea": 123.0,
      "yearBuilt": 0,
      "streetCode": 0,
      "settlmentID": 3000,
      "buildingFloors": 0,
      "hokHamecher": 0,
      "trend": {
        "rate": 0,
        "years": 0
      },
      "prevDeals": [],
      "ownership": [],
      "priceSM": 29496,
      "row_id": 25
    },
    {
      "assetId": 4467940.0,
      "addressId": 66105762,
      "polygonId": "52555733",
      "neighborhoodName": "מרכז העיר מזרח",
      "neighborhoodId": 65209838,
      "address": "קונדר 6",
      "dealDate": "2024-02-05",
      "dealAmount": 210000,
      "parcelNum": "30821-47-3",
      "dealNature": "דירה בבית קומות",
      "roomNum": 3.0,
      "floor": "ראשונה",
      "assetArea": 100.0,
      "yearBuilt": 1920,
      "streetCode": 30000217,
      "settlmentID": 3000,
      "buildingFloors": 1,
      "hokHamecher": 0,
      "trend": {
        "rate": 0,
        "years": 0
      },
      "prevDeals": [],
      "ownership": [],
      "priceSM": 2100,
      "row_id": 27
    },
    {
      "assetId": 4227883.0,
      "addressId": 0,
      "polygonId": "30092-31",
      "neighborhoodName": "מרכז העיר מזרח",
      "neighborhoodId": 65209838,
      "address": "0",
      "dealDate": "2023-12-07",
      "dealAmount": 2786000,
      "parcelNum": "30092-31-47",
      "dealNature": "דירה בבית קומות",
      "roomNum": 3.0,
      "floor": "שש עשרה",
      "assetArea": 82.0,
      "yearBuilt": 0,
      "streetCode": 0,
      "settlmentID": 3000,
      "buildingFloors": 0,
      "hokHamecher": 0,
      "trend": {
        "rate": 0,
        "years": 0
      },
      "prevDeals": [],
      "ownership": [],
      "priceSM": 33976,
      "row_id": 28
    },
    {
      "assetId": 4227883.0,
      "addressId": 0,
      "polygonId": "30092-31",
      "neighborhoodName": "מרכז העיר מזרח",
      "neighborhoodId": 65209838,
      "address": "0",
      "dealDate": "2023-12-06",
      "dealAmount": 3628000,
      "parcelNum": "30092-31-48",
      "dealNature": "דירה בבית קומות",
      "roomNum": 5.0,
      "floor": "שתים עשרה",
      "assetArea": 123.0,
      "yearBuilt": 0,
      "streetCode": 0,
      "settlmentID": 3000,
      "buildingFloors": 0,
      "hokHamecher": 0,
      "trend": {
        "rate": 0,
        "years": 0
      },
      "prevDeals": [],
      "ownership": [],
      "priceSM": 29496,
      "row_id": 30
    },
    {
      "assetId": 4227883.0,
      "addressId": 0,
      "polygonId": "30092-31",
      "neighborhoodName": "מרכז העיר מזרח",
      "neighborhoodId": 65209838,
      "address": "0",
      "dealDate": "2023-11-26",
      "dealAmount": 3361000,
      "parcelNum": "30092-31-49",
      "dealNature": "דירה בבית קומות",
      "roomNum": 4.0,
      "floor": "עשרים ושתיים",
      "assetArea": 96.0,
      "yearBuilt": 0,
      "streetCode": 0,
      "settlmentID": 3000,
      "buildingFloors": 0,
      "hokHamecher": 0,
      "trend": {
        "rate": 0,
        "years": 0
      },
      "prevDeals": [],
      "ownership": [],
      "priceSM": 35010,
      "row_id": 33
    },
    {
      "assetId": 4227883.0,
      "addressId": 0,
      "polygonId": "30092-31",
      "neighborhoodName": "מרכז העיר מזרח",
      "neighborhoodId": 65209838,
      "address": "0",
      "dealDate": "2023-09-13",
      "dealAmount": 3658000,
      "parcelNum": "30092-31-50",
      "dealNature": "דירה בבית קומות",
      "roomNum": 5.0,
      "floor": "שלוש עשרה",
      "assetArea": 123.0,
      "yearBuilt": 0,
      "streetCode": 0,
      "settlmentID": 3000,
      "buildingFloors": 0,
      "hokHamecher": 0,
      "trend": {
        "rate": 0,
        "years": 0
      },
      "prevDeals": [],
      "ownership": [],
      "priceSM": 29740,
      "row_id": 35
    },
    {
      "assetId": 4227883.0,
      "addressId": 0,
      "polygonId": "30092-31",
      "neighborhoodName": "מרכז העיר מזרח",
      "neighborhoodId": 65209838,
      "address": "0",
      "dealDate": "2023-08-22",
      "dealAmount": 3331000,
      "parcelNum": "30092-31-51",
      "dealNature": "דירה בבית קומות",
      "roomNum": 4.0,
      "floor": "שבע עשרה",
      "assetArea": 96.0,
      "yearBuilt": 0,
      "streetCode": 0,
      "settlmentID": 3000,
      "buildingFloors": 0,
      "hokHamecher": 0,
      "prevDeals": [
        {
          "dealDate": "2023-08-22",
          "dealAmount": 3241000
        },
        {
          "dealDate": "2023-08-22",
          "dealAmount": 3211000
        }
      ],
      "trend": {
        "rate": 2.8,
        "years": 0.0
      },
      "ownership": [],
      "priceSM": 34698,
      "row_id": 37
    },
    {
      "assetId": 4227883.0,
      "addressId": 0,
      "polygonId": "30092-31",
      "neighborhoodName": "מרכז העיר מזרח",
      "neighborhoodId": 65209838,
      "address": "0",
      "dealDate": "2023-07-30",
      "dealAmount": 2845000,
      "parcelNum": "30092-31-54",
      "dealNature": "דירה בבית קומות",
      "roomNum": 3.0,
      "floor": "חמש עשרה",
      "assetArea": 82.0,
      "yearBuilt": 0,
      "streetCode": 0,
      "settlmentID": 3000,
      "buildingFloors": 0,
      "hokHamecher": 0,
      "trend": {
        "rate": 0,
        "years": 0
      },
      "prevDeals": [],
      "ownership": [],
      "priceSM": 34695,
      "row_id": 41
    },
    {
      "assetId": 4227883.0,
      "addressId": 0,
      "polygonId": "30092-31",
      "neighborhoodName": "מרכז העיר מזרח",
      "neighborhoodId": 65209838,
      "address": "0",
      "dealDate": "2023-06-29",
      "dealAmount": 3451000,
      "parcelNum": "30092-31-55",
      "dealNature": "דירה בבית קומות",
      "roomNum": 4.0,
      "floor": "עשרים וחמש",
      "assetArea": 96.0,
      "yearBuilt": 0,
      "streetCode": 0,
      "settlmentID": 3000,
      "buildingFloors": 0,
      "hokHamecher": 0,
      "trend": {
        "rate": 0,
        "years": 0
      },
      "prevDeals": [],
      "ownership": [],
      "priceSM": 35948,
      "row_id": 43
    },
    {
      "assetId": 4227883.0,
      "addressId": 0,
      "polygonId": "30092-31",
      "neighborhoodName": "מרכז העיר מזרח",
      "neighborhoodId": 65209838,
      "address": "0",
      "dealDate": "2023-06-19",
      "dealAmount": 3628000,
      "parcelNum": "30092-31-56",
      "dealNature": "דירה בבית קומות",
      "roomNum": 5.0,
      "floor": "אחת עשרה",
      "assetArea": 123.0,
      "yearBuilt": 0,
      "streetCode": 0,
      "settlmentID": 3000,
      "buildingFloors": 0,
      "hokHamecher": 0,
      "trend": {
        "rate": 0,
        "years": 0
      },
      "prevDeals": [],
      "ownership": [],
      "priceSM": 29496,
      "row_id": 44
    },
    {
      "assetId": 4227883.0,
      "addressId": 0,
      "polygonId": "30092-31",
      "neighborhoodName": "מרכז העיר מזרח",
      "neighborhoodId": 65209838,
      "address": "0",
      "dealDate": "2023-06-12",
      "dealAmount": 4138000,
      "parcelNum": "30092-31-57",
      "dealNature": "דירה בבית קומות",
      "roomNum": 5.0,
      "floor": "עשרים ותשע",
      "assetArea": 123.0,
      "yearBuilt": 0,
      "streetCode": 0,
      "settlmentID": 3000,
      "buildingFloors": 0,
      "hokHamecher": 0,
      "trend": {
        "rate": 0,
        "years": 0
      },
      "prevDeals": [],
      "ownership": [],
      "priceSM": 33642,
      "row_id": 45
    },
    {
      "assetId": 4227883.0,
      "addressId": 0,
      "polygonId": "30092-31",
      "neighborhoodName": "מרכז העיר מזרח",
      "neighborhoodId": 65209838,
      "address": "0",
      "dealDate": "2023-06-08",
      "dealAmount": 3798000,
      "parcelNum": "30092-31-58",
      "dealNature": "דירה בבית קומות",
      "roomNum": 5.0,
      "floor": "שש עשרה",
      "assetArea": 123.0,
      "yearBuilt": 0,
      "streetCode": 0,
      "settlmentID": 3000,
      "buildingFloors": 0,
      "hokHamecher": 0,
      "prevDeals": [
        {
          "dealDate": "2023-06-08",
          "dealAmount": 3628000
        },
        {
          "dealDate": "2023-06-08",
          "dealAmount": 3768000
        }
      ],
      "trend": {
        "rate": 4.7,
        "years": 0.0
      },
      "ownership": [],
      "priceSM": 30878,
      "row_id": 46
    },
    {
      "assetId": 4227883.0,
      "addressId": 0,
      "polygonId": "30092-31",
      "neighborhoodName": "מרכז העיר מזרח",
      "neighborhoodId": 65209838,
      "address": "0",
      "dealDate": "2023-05-15",
      "dealAmount": 4078000,
      "parcelNum": "30092-31-62",
      "dealNature": "דירה בבית קומות",
      "roomNum": 5.0,
      "floor": "עשרים ושש",
      "assetArea": 123.0,
      "yearBuilt": 0,
      "streetCode": 0,
      "settlmentID": 3000,
      "buildingFloors": 0,
      "hokHamecher": 0,
      "prevDeals": [
        {
          "dealDate": "2023-05-15",
          "dealAmount": 4108000
        },
        {
          "dealDate": "2023-05-15",
          "dealAmount": 4048000
        }
      ],
      "trend": {
        "rate": -0.7,
        "years": 0.0
      },
      "ownership": [],
      "priceSM": 33154,
      "row_id": 47
    },
    {
      "assetId": 4301911.0,
      "addressId": 0,
      "polygonId": "30821-32",
      "neighborhoodName": "מרכז העיר מזרח",
      "neighborhoodId": 65209838,
      "address": "0",
      "dealDate": "2023-05-04",
      "dealAmount": 1000000,
      "parcelNum": "30821-32-1",
      "dealNature": "דירה בבית קומות",
      "roomNum": 2.0,
      "floor": "ראשונה",
      "assetArea": 57.0,
      "yearBuilt": 0,
      "streetCode": 0,
      "settlmentID": 3000,
      "buildingFloors": 0,
      "hokHamecher": 0,
      "trend": {
        "rate": 0,
        "years": 0
      },
      "prevDeals": [],
      "ownership": [],
      "priceSM": 17544,
      "row_id": 49
    },
    {
      "assetId": 4227883.0,
      "addressId": 0,
      "polygonId": "30092-31",
      "neighborhoodName": "מרכז העיר מזרח",
      "neighborhoodId": 65209838,
      "address": "0",
      "dealDate": "2023-04-03",
      "dealAmount": 4099000,
      "parcelNum": "30092-31-65",
      "dealNature": "דירה בבית קומות",
      "roomNum": 5.0,
      "floor": "שש עשרה",
      "assetArea": 123.0,
      "yearBuilt": 0,
      "streetCode": 0,
      "settlmentID": 3000,
      "buildingFloors": 0,
      "hokHamecher": 0,
      "prevDeals": [
        {
          "dealDate": "2023-04-03",
          "dealAmount": 2785000
        },
        {
          "dealDate": "2023-04-03",
          "dealAmount": 3030000
        }
      ],
      "trend": {
        "rate": 47.2,
        "years": 0.0
      },
      "ownership": [],
      "priceSM": 33325,
      "row_id": 50
    },
    {
      "assetId": 4227780.0,
      "addressId": 0,
      "polygonId": "30092-31",
      "neighborhoodName": "מרכז העיר מזרח",
      "neighborhoodId": 65209838,
      "address": "0",
      "dealDate": "2023-03-09",
      "dealAmount": 3718000,
      "parcelNum": "30092-31-6",
      "dealNature": "דירה בבית קומות",
      "roomNum": 5.0,
      "floor": "חמש עשרה",
      "assetArea": 123.0,
      "yearBuilt": 0,
      "streetCode": 0,
      "settlmentID": 3000,
      "buildingFloors": 0,
      "hokHamecher": 0,
      "trend": {
        "rate": 0,
        "years": 0
      },
      "prevDeals": [],
      "ownership": [],
      "priceSM": 30228,
      "row_id": 51
    },
    {
      "assetId": 4227763.0,
      "addressId": 0,
      "polygonId": "30092-31",
      "neighborhoodName": "מרכז העיר מזרח",
      "neighborhoodId": 65209838,
      "address": "0",
      "dealDate": "2023-03-09",
      "dealAmount": 4219000,
      "parcelNum": "30092-31-7",
      "dealNature": "דירה בבית קומות",
      "roomNum": 5.0,
      "floor": "עשרים וחמש",
      "assetArea": 123.0,
      "yearBuilt": 0,
      "streetCode": 0,
      "settlmentID": 3000,
      "buildingFloors": 0,
      "hokHamecher": 0,
      "trend": {
        "rate": 0,
        "years": 0
      },
      "prevDeals": [],
      "ownership": [],
      "priceSM": 34301,
      "row_id": 52
    },
    {
      "assetId": 4227883.0,
      "addressId": 0,
      "polygonId": "30092-31",
      "neighborhoodName": "מרכז העיר מזרח",
      "neighborhoodId": 65209838,
      "address": "0",
      "dealDate": "2023-03-02",
      "dealAmount": 3301000,
      "parcelNum": "30092-31-68",
      "dealNature": "דירה בבית קומות",
      "roomNum": 4.0,
      "floor": "עשרים",
      "assetArea": 97.0,
      "yearBuilt": 0,
      "streetCode": 0,
      "settlmentID": 3000,
      "buildingFloors": 0,
      "hokHamecher": 0,
      "trend": {
        "rate": 0,
        "years": 0
      },
      "prevDeals": [],
      "ownership": [],
      "priceSM": 34031,
      "row_id": 53
    },
    {
      "assetId": 4227883.0,
      "addressId": 0,
      "polygonId": "30092-31",
      "neighborhoodName": "מרכז העיר מזרח",
      "neighborhoodId": 65209838,
      "address": "0",
      "dealDate": "2022-12-05",
      "dealAmount": 2668000,
      "parcelNum": "30092-31-69",
      "dealNature": "דירה בבית קומות",
      "roomNum": 4.0,
      "floor": "ראשונה",
      "assetArea": 106.0,
      "yearBuilt": 0,
      "streetCode": 0,
      "settlmentID": 3000,
      "buildingFloors": 0,
      "hokHamecher": 0,
      "prevDeals": [
        {
          "dealDate": "2022-12-05",
          "dealAmount": 1155000
        },
        {
          "dealDate": "2022-12-05",
          "dealAmount": 403000
        },
        {
          "dealDate": "2022-12-05",
          "dealAmount": 2393000
        },
        {
          "dealDate": "2022-12-05",
          "dealAmount": 4091000
        },
        {
          "dealDate": "2022-12-05",
          "dealAmount": 2972000
        }
      ],
      "trend": {
        "rate": 131.0,
        "years": 0.0
      },
      "ownership": [],
      "priceSM": 25170,
      "row_id": 55
    },
    {
      "assetId": 4227833.0,
      "addressId": 0,
      "polygonId": "30092-31",
      "neighborhoodName": "מרכז העיר מזרח",
      "neighborhoodId": 65209838,
      "address": "0",
      "dealDate": "2022-12-05",
      "dealAmount": 5464000,
      "parcelNum": "30092-31-5",
      "dealNature": "דירה בבית קומות",
      "roomNum": 2.0,
      "floor": "ראשונה",
      "assetArea": 39.0,
      "yearBuilt": 0,
      "streetCode": 0,
      "settlmentID": 3000,
      "buildingFloors": 0,
      "hokHamecher": 0,
      "trend": {
        "rate": 0,
        "years": 0
      },
      "prevDeals": [],
      "ownership": [],
      "priceSM": 140103,
      "row_id": 56
    },
    {
      "assetId": 4301928.0,
      "addressId": 0,
      "polygonId": "30821-33",
      "neighborhoodName": "מרכז העיר מזרח",
      "neighborhoodId": 65209838,
      "address": "0",
      "dealDate": "2022-05-12",
      "dealAmount": 50000,
      "parcelNum": "30821-33-1",
      "dealNature": "דירה בבית קומות",
      "roomNum": 3.0,
      "floor": "ראשונה",
      "assetArea": 30.0,
      "yearBuilt": 0,
      "streetCode": 0,
      "settlmentID": 3000,
      "buildingFloors": 0,
      "hokHamecher": 0,
      "trend": {
        "rate": 0,
        "years": 0
      },
      "prevDeals": [],
      "ownership": [],
      "priceSM": 1667,
      "row_id": 62
    },
    {
      "assetId": 4467941.0,
      "addressId": 66105762,
      "polygonId": "52555733",
      "neighborhoodName": "מרכז העיר מזרח",
      "neighborhoodId": 65209838,
      "address": "קונדר 6",
      "dealDate": "2021-12-27",
      "dealAmount": 150000,
      "parcelNum": "30821-47-2",
      "dealNature": "דירה בבית קומות",
      "roomNum": 3.0,
      "floor": "ראשונה",
      "assetArea": 100.0,
      "yearBuilt": 1920,
      "streetCode": 30000217,
      "settlmentID": 3000,
      "buildingFloors": 1,
      "hokHamecher": 0,
      "trend": {
        "rate": 0,
        "years": 0
      },
      "prevDeals": [],
      "ownership": [],
      "priceSM": 1500,
      "row_id": 63
    },
    {
      "assetId": 4227883.0,
      "addressId": 0,
      "polygonId": "30092-31",
      "neighborhoodName": "מרכז העיר מזרח",
      "neighborhoodId": 65209838,
      "address": "0",
      "dealDate": "2019-12-01",
      "dealAmount": 1300000,
      "parcelNum": "30092-31-151",
      "dealNature": "דירה בבית קומות",
      "roomNum": 3.0,
      "floor": "רביעית",
      "assetArea": 40.0,
      "yearBuilt": 0,
      "streetCode": 0,
      "settlmentID": 3000,
      "buildingFloors": 0,
      "hokHamecher": 0,
      "trend": {
        "rate": 0,
        "years": 0
      },
      "prevDeals": [],
      "ownership": [],
      "priceSM": 32500,
      "row_id": 67
    },
    {
      "assetId": 4301912.0,
      "addressId": 0,
      "polygonId": "30821-30",
      "neighborhoodName": "מרכז העיר מזרח",
      "neighborhoodId": 65209838,
      "address": "0",
      "dealDate": "2019-11-20",
      "dealAmount": 52000,
      "parcelNum": "30821-30-4",
      "dealNature": "דירה בבית קומות",
      "roomNum": 1.0,
      "floor": null,
      "assetArea": 43.0,
      "yearBuilt": 0,
      "streetCode": 0,
      "settlmentID": 3000,
      "buildingFloors": 0,
      "hokHamecher": 0,
      "trend": {
        "rate": 0,
        "years": 0
      },
      "prevDeals": [],
      "ownership": [],
      "priceSM": 1209,
      "row_id": 68
    },
    {
      "assetId": 4227890.0,
      "addressId": 66105761,
      "polygonId": "52555733",
      "neighborhoodName": "מרכז העיר מזרח",
      "neighborhoodId": 65209838,
      "address": "קונדר 4",
      "dealDate": "2018-02-13",
      "dealAmount": 614000,
      "parcelNum": "30092-41-1",
      "dealNature": "דירה בבית קומות",
      "roomNum": 1.0,
      "floor": "ראשונה",
      "assetArea": 30.0,
      "yearBuilt": 0,
      "streetCode": 30000217,
      "settlmentID": 3000,
      "buildingFloors": 0,
      "hokHamecher": 0,
      "trend": {
        "rate": 0,
        "years": 0
      },
      "prevDeals": [],
      "ownership": [],
      "priceSM": 20467,
      "row_id": 70
    },
    {
      "assetId": 4301842.0,
      "addressId": 0,
      "polygonId": "30821-30",
      "neighborhoodName": "מרכז העיר מזרח",
      "neighborhoodId": 65209838,
      "address": "0",
      "dealDate": "2017-12-05",
      "dealAmount": 100000,
      "parcelNum": "30821-30-1",
      "dealNature": "דירה בבית קומות",
      "roomNum": 2.0,
      "floor": null,
      "assetArea": 45.0,
      "yearBuilt": 0,
      "streetCode": 0,
      "settlmentID": 3000,
      "buildingFloors": 0,
      "hokHamecher": 0,
      "trend": {
        "rate": 0,
        "years": 0
      },
      "prevDeals": [],
      "ownership": [],
      "priceSM": 2222,
      "row_id": 71
    },
    {
      "assetId": 4471870.0,
      "addressId": 66126434,
      "polygonId": "52651489",
      "neighborhoodName": "מרכז העיר מזרח",
      "neighborhoodId": 65209838,
      "address": "דלמן 5",
      "dealDate": "2017-01-05",
      "dealAmount": 64000,
      "parcelNum": "30821-10-1",
      "dealNature": "דירה בבית קומות",
      "roomNum": 3.0,
      "floor": "ראשונה",
      "assetArea": 48.0,
      "yearBuilt": 1940,
      "streetCode": 30000211,
      "settlmentID": 3000,
      "buildingFloors": 1,
      "hokHamecher": 0,
      "trend": {
        "rate": 0,
        "years": 0
      },
      "prevDeals": [],
      "ownership": [],
      "priceSM": 1333,
      "row_id": 72
    },
    {
      "assetId": 4226924.0,
      "addressId": 0,
      "polygonId": "30090-17",
      "neighborhoodName": "מרכז העיר מזרח",
      "neighborhoodId": 65209838,
      "address": "0",
      "dealDate": "2011-02-14",
      "dealAmount": 1481600,
      "parcelNum": "30090-17-1",
      "dealNature": "דירה בבית קומות",
      "roomNum": 2.0,
      "floor": "ראשונה",
      "assetArea": 60.0,
      "yearBuilt": 0,
      "streetCode": 0,
      "settlmentID": 3000,
      "buildingFloors": 0,
      "hokHamecher": 0,
      "trend": {
        "rate": 0,
        "years": 0
      },
      "prevDeals": [],
      "ownership": [],
      "priceSM": 24693,
      "row_id": 78
    },
    {
      "assetId": 4227897.0,
      "addressId": 66105762,
      "polygonId": "52555733",
      "neighborhoodName": "מרכז העיר מזרח",
      "neighborhoodId": 65209838,
      "address": "קונדר 6",
      "dealDate": "2010-11-21",
      "dealAmount": 399000,
      "parcelNum": "30092-47-2",
      "dealNature": "דירה בבית קומות",
      "roomNum": 3.0,
      "floor": "ראשונה",
      "assetArea": 70.0,
      "yearBuilt": 0,
      "streetCode": 30000217,
      "settlmentID": 3000,
      "buildingFloors": 0,
      "hokHamecher": 0,
      "trend": {
        "rate": 0,
        "years": 0
      },
      "prevDeals": [],
      "ownership": [],
      "priceSM": 5700,
      "row_id": 80
    },
    {
      "assetId": 4227894.0,
      "addressId": 66105761,
      "polygonId": "52555733",
      "neighborhoodName": "מרכז העיר מזרח",
      "neighborhoodId": 65209838,
      "address": "קונדר 4",
      "dealDate": "2010-10-31",
      "dealAmount": 418000,
      "parcelNum": "30092-42-1",
      "dealNature": "דירה בבית קומות",
      "roomNum": 3.0,
      "floor": "ראשונה",
      "assetArea": 76.0,
      "yearBuilt": 0,
      "streetCode": 30000217,
      "settlmentID": 3000,
      "buildingFloors": 0,
      "hokHamecher": 0,
      "trend": {
        "rate": 0,
        "years": 0
      },
      "prevDeals": [],
      "ownership": [],
      "priceSM": 5500,
      "row_id": 81
    },
    {
      "assetId": 4470947.0,
      "addressId": 66118045,
      "polygonId": "52601118",
      "neighborhoodName": "מרכז העיר מזרח",
      "neighborhoodId": 65209838,
      "address": "קונדר 3",
      "dealDate": "2007-12-24",
      "dealAmount": 1365000,
      "parcelNum": "30506-5-1",
      "dealNature": "דירה בבית קומות",
      "roomNum": 5.0,
      "floor": "ראשונה",
      "assetArea": 140.0,
      "yearBuilt": 1956,
      "streetCode": 30000217,
      "settlmentID": 3000,
      "buildingFloors": 1,
      "hokHamecher": 0,
      "trend": {
        "rate": 0,
        "years": 0
      },
      "prevDeals": [],
      "ownership": [],
      "priceSM": 9750,
      "row_id": 82
    },
    {
      "assetId": 4210253.0,
      "addressId": 0,
      "polygonId": "30055-63",
      "neighborhoodName": "מרכז העיר מזרח",
      "neighborhoodId": 65209838,
      "address": "0",
      "dealDate": "2004-01-11",
      "dealAmount": 140000,
      "parcelNum": "30055-63-1",
      "dealNature": "דירה בבית קומות",
      "roomNum": 1.0,
      "floor": null,
      "assetArea": 0.0,
      "yearBuilt": 0,
      "streetCode": 0,
      "settlmentID": 3000,
      "buildingFloors": 0,
      "hokHamecher": 0,
      "trend": {
        "rate": 0,
        "years": 0
      },
      "prevDeals": [],
      "ownership": [],
      "priceSM": 0,
      "row_id": 84
    },
    {
      "assetId": 4227903.0,
      "addressId": 66105758,
      "polygonId": "52651489",
      "neighborhoodName": "מרכז העיר מזרח",
      "neighborhoodId": 65209838,
      "address": "דלמן 3",
      "dealDate": "2003-10-22",
      "dealAmount": 184000,
      "parcelNum": "30092-50-1",
      "dealNature": "דירה בבית קומות",
      "roomNum": 0.0,
      "floor": null,
      "assetArea": 50.0,
      "yearBuilt": 0,
      "streetCode": 30000211,
      "settlmentID": 3000,
      "buildingFloors": 0,
      "hokHamecher": 0,
      "trend": {
        "rate": 0,
        "years": 0
      },
      "prevDeals": [],
      "ownership": [],
      "priceSM": 3680,
      "row_id": 85
    }
  ]
}