{
  "neighborhood_name": "שבזי",
  "city_name": "ראש העין",
  "transaction_count": 76,
  "transactions": [
    {
      "assetId": 4492563.0,
      "addressId": 53909516,
      "polygonId": "53093886",
      "neighborhoodName": "שבזי",
      "neighborhoodId": 65210556,
      "address": "אפק 83",
      "dealDate": "2025-06-11",
      "dealAmount": 845000,
      "parcelNum": "4270-160-1",
      "dealNature": "קרקע למגורים",
      "roomNum": 0.0,
      "floor": null,
      "assetArea": 32.0,
      "yearBuilt": 0,
      "streetCode": 26400143,
      "settlmentID": 2640,
      "buildingFloors": 0,
      "hokHamecher": 0,
      "trend": {
        "rate": 0,
        "years": 0
      },
      "prevDeals": [],
      "ownership": [],
      "priceSM": 26406,
      "row_id": 1
    },
    {
      "assetId": 80007528.0,
      "addressId": 53907604,
      "polygonId": "71177159",
      "neighborhoodName": "שבזי",
      "neighborhoodId": 65210556,
      "address": "יעקב ספיר 3",
      "dealDate": "2025-02-18",
      "dealAmount": 2200000,
      "parcelNum": "4271-127-1",
      "dealNature": "דירה בבית קומות",
      "roomNum": 4.0,
      "floor": "ראשונה",
      "assetArea": 100.0,
      "yearBuilt": 2021,
      "streetCode": 26400145,
      "settlmentID": 2640,
      "buildingFloors": 0,
      "hokHamecher": 0,
      "prevDeals": [
        {
          "dealDate": "2022-02-09",
          "dealAmount": 458000
        },
        {
          "dealDate": "2021-11-11",
          "dealAmount": 458000
        },
        {
          "dealDate": "2021-11-11",
          "dealAmount": 464000
        },
        {
          "dealDate": "2021-11-04",
          "dealAmount": 461000
        },
        {
          "dealDate": "2021-10-28",
          "dealAmount": 452000
        },
        {
          "dealDate": "2021-02-14",
          "dealAmount": 630000
        },
        {
          "dealDate": "2021-01-28",
          "dealAmount": 450000
        },
        {
          "dealDate": "2020-08-10",
          "dealAmount": 450000
        },
        {
          "dealDate": "2019-05-19",
          "dealAmount": 5734000
        }
      ],
      "trend": {
        "rate": 380.3,
        "years": 3.0
      },
      "ownership": [],
      "priceSM": 22000,
      "row_id": 2
    },
    {
      "assetId": 80006920.0,
      "addressId": 53733831,
      "polygonId": "71177206",
      "neighborhoodName": "שבזי",
      "neighborhoodId": 65210556,
      "address": "שבזי 114",
      "dealDate": "2024-09-08",
      "dealAmount": 1356000,
      "parcelNum": "4270-68-1",
      "dealNature": "קרקע למגורים",
      "roomNum": 5.0,
      "floor": null,
      "assetArea": 1442.0,
      "yearBuilt": 2003,
      "streetCode": 26400142,
      "settlmentID": 2640,
      "buildingFloors": 1,
      "hokHamecher": 0,
      "prevDeals": [
        {
          "dealDate": "2005-07-28",
          "dealAmount": 4599000
        },
        {
          "dealDate": "2005-03-16",
          "dealAmount": 698000
        }
      ],
      "trend": {
        "rate": -70.5,
        "years": 19.1
      },
      "ownership": [],
      "priceSM": 940,
      "row_id": 3
    },
    {
      "assetId": 80006840.0,
      "addressId": 53728343,
      "polygonId": "52317252",
      "neighborhoodName": "שבזי",
      "neighborhoodId": 65210556,
      "address": "בעל מלאכת שלמה 11",
      "dealDate": "2024-09-03",
      "dealAmount": 1550000,
      "parcelNum": "4270-46-2",
      "dealNature": "דירה בבית קומות",
      "roomNum": 4.0,
      "floor": "קרקע",
      "assetArea": 84.55,
      "yearBuilt": 1950,
      "streetCode": 26400144,
      "settlmentID": 2640,
      "buildingFloors": 0,
      "hokHamecher": 0,
      "prevDeals": [
        {
          "dealDate": "2021-09-14",
          "dealAmount": 750000
        }
      ],
      "trend": {
        "rate": 106.7,
        "years": 3.0
      },
      "ownership": [],
      "priceSM": 18452,
      "row_id": 4
    },
    {
      "assetId": 80008136.0,
      "addressId": 53910415,
      "polygonId": "52336420",
      "neighborhoodName": "שבזי",
      "neighborhoodId": 65210556,
      "address": "דקר 37",
      "dealDate": "2024-08-16",
      "dealAmount": 232000,
      "parcelNum": "4272-97-1",
      "dealNature": "קרקע למגורים",
      "roomNum": 0.0,
      "floor": "קרקע",
      "assetArea": 100.8,
      "yearBuilt": 0,
      "streetCode": 26400149,
      "settlmentID": 2640,
      "buildingFloors": 1,
      "hokHamecher": 0,
      "trend": {
        "rate": 0,
        "years": 0
      },
      "prevDeals": [],
      "ownership": [],
      "priceSM": 2302,
      "row_id": 5
    },
    {
      "assetId": 81318617.0,
      "addressId": 53906110,
      "polygonId": "71177175",
      "neighborhoodName": "שבזי",
      "neighborhoodId": 65210556,
      "address": "אפק 38",
      "dealDate": "2024-08-14",
      "dealAmount": 1800000,
      "parcelNum": "4271-98-1",
      "dealNature": "מגורים",
      "roomNum": 0.0,
      "floor": null,
      "assetArea": 250.0,
      "yearBuilt": 0,
      "streetCode": 26400143,
      "settlmentID": 2640,
      "buildingFloors": 0,
      "hokHamecher": 0,
      "trend": {
        "rate": 0,
        "years": 0
      },
      "prevDeals": [],
      "ownership": [],
      "priceSM": 7200,
      "row_id": 6
    },
    {
      "assetId": 80007425.0,
      "addressId": 53810879,
      "polygonId": "52236233",
      "neighborhoodName": "שבזי",
      "neighborhoodId": 65210556,
      "address": "אפק 32",
      "dealDate": "2023-12-04",
      "dealAmount": 3050000,
      "parcelNum": "4271-100-2",
      "dealNature": "קוטג' טורי",
      "roomNum": 4.0,
      "floor": "ראשונה",
      "assetArea": 105.0,
      "yearBuilt": 1950,
      "streetCode": 26400143,
      "settlmentID": 2640,
      "buildingFloors": 0,
      "hokHamecher": 0,
      "prevDeals": [
        {
          "dealDate": "2021-04-05",
          "dealAmount": 1900000
        }
      ],
      "trend": {
        "rate": 60.5,
        "years": 2.7
      },
      "ownership": [],
      "priceSM": 29048,
      "row_id": 8
    },
    {
      "assetId": 80007476.0,
      "addressId": 53908778,
      "polygonId": "53303048",
      "neighborhoodName": "שבזי",
      "neighborhoodId": 65210556,
      "address": "ארץ ישראל השלמה 10",
      "dealDate": "2023-07-19",
      "dealAmount": 680000,
      "parcelNum": "4271-111-1",
      "dealNature": "קרקע למגורים",
      "roomNum": 0.0,
      "floor": "ראשונה",
      "assetArea": 21.87,
      "yearBuilt": 1960,
      "streetCode": 26400156,
      "settlmentID": 2640,
      "buildingFloors": 0,
      "hokHamecher": 0,
      "prevDeals": [
        {
          "dealDate": "2022-04-03",
          "dealAmount": 1890000
        },
        {
          "dealDate": "2019-06-30",
          "dealAmount": 660000
        },
        {
          "dealDate": "2017-06-29",
          "dealAmount": 2400000
        }
      ],
      "trend": {
        "rate": -64.0,
        "years": 1.3
      },
      "ownership": [],
      "priceSM": 32381,
      "row_id": 9
    },
    {
      "assetId": 80006910.0,
      "addressId": 0,
      "polygonId": "52269703",
      "neighborhoodName": "שבזי",
      "neighborhoodId": 65210556,
      "address": "בעל מלאכת שלמה 6",
      "dealDate": "2023-06-26",
      "dealAmount": 1300000,
      "parcelNum": "4270-65-1",
      "dealNature": "דירה בבית קומות",
      "roomNum": 5.0,
      "floor": "ראשונה",
      "assetArea": 100.0,
      "yearBuilt": 1960,
      "streetCode": 26400144,
      "settlmentID": 2640,
      "buildingFloors": 0,
      "hokHamecher": 0,
      "prevDeals": [
        {
          "dealDate": "2023-02-26",
          "dealAmount": 1750000
        },
        {
          "dealDate": "2022-02-17",
          "dealAmount": 395000
        },
        {
          "dealDate": "2021-12-06",
          "dealAmount": 915000
        },
        {
          "dealDate": "2021-01-03",
          "dealAmount": 2825000
        }
      ],
      "trend": {
        "rate": -25.7,
        "years": 0.3
      },
      "ownership": [],
      "priceSM": 13000,
      "row_id": 10
    },
    {
      "assetId": 80006867.0,
      "addressId": 53732563,
      "polygonId": "52335912",
      "neighborhoodName": "שבזי",
      "neighborhoodId": 65210556,
      "address": "אפק 82",
      "dealDate": "2023-04-02",
      "dealAmount": 3550000,
      "parcelNum": "4270-53-2",
      "dealNature": "קרקע למגורים",
      "roomNum": 0.0,
      "floor": "קרקע",
      "assetArea": 47.1,
      "yearBuilt": 1970,
      "streetCode": 26400143,
      "settlmentID": 2640,
      "buildingFloors": 0,
      "hokHamecher": 0,
      "trend": {
        "rate": 0,
        "years": 0
      },
      "prevDeals": [],
      "ownership": [],
      "priceSM": 75372,
      "row_id": 11
    },
    {
      "assetId": 80006913.0,
      "addressId": 53733056,
      "polygonId": "71177169",
      "neighborhoodName": "שבזי",
      "neighborhoodId": 65210556,
      "address": "שבזי 122",
      "dealDate": "2023-03-23",
      "dealAmount": 312000,
      "parcelNum": "4270-66-1",
      "dealNature": "דירה בבית קומות",
      "roomNum": 7.0,
      "floor": "ראשונה",
      "assetArea": 148.0,
      "yearBuilt": 1990,
      "streetCode": 26400142,
      "settlmentID": 2640,
      "buildingFloors": 1,
      "hokHamecher": 0,
      "prevDeals": [
        {
          "dealDate": "2017-12-11",
          "dealAmount": 625000
        },
        {
          "dealDate": "2017-12-05",
          "dealAmount": 625000
        },
        {
          "dealDate": "2005-07-18",
          "dealAmount": 1551000
        }
      ],
      "trend": {
        "rate": -50.1,
        "years": 5.3
      },
      "ownership": [],
      "priceSM": 2108,
      "row_id": 12
    },
    {
      "assetId": 80006911.0,
      "addressId": 0,
      "polygonId": "52269703",
      "neighborhoodName": "שבזי",
      "neighborhoodId": 65210556,
      "address": "בעל מלאכת שלמה 6",
      "dealDate": "2023-03-08",
      "dealAmount": 1710000,
      "parcelNum": "4270-65-2",
      "dealNature": "קרקע למגורים",
      "roomNum": 0.0,
      "floor": null,
      "assetArea": 21.87,
      "yearBuilt": 1960,
      "streetCode": 26400144,
      "settlmentID": 2640,
      "buildingFloors": 0,
      "hokHamecher": 0,
      "trend": {
        "rate": 0,
        "years": 0
      },
      "prevDeals": [],
      "ownership": [],
      "priceSM": 78189,
      "row_id": 13
    },
    {
      "assetId": 80007058.0,
      "addressId": 53734354,
      "polygonId": "52320685",
      "neighborhoodName": "שבזי",
      "neighborhoodId": 65210556,
      "address": "שבטי ישראל 18",
      "dealDate": "2022-12-25",
      "dealAmount": 985000,
      "parcelNum": "4270-119-1",
      "dealNature": "דירה בבית קומות",
      "roomNum": 5.0,
      "floor": "קרקע",
      "assetArea": 161.0,
      "yearBuilt": 1982,
      "streetCode": 26400163,
      "settlmentID": 2640,
      "buildingFloors": 0,
      "hokHamecher": 0,
      "trend": {
        "rate": 0,
        "years": 0
      },
      "prevDeals": [],
      "ownership": [],
      "priceSM": 6118,
      "row_id": 15
    },
    {
      "assetId": 81307699.0,
      "addressId": 53727292,
      "polygonId": "52335443",
      "neighborhoodName": "שבזי",
      "neighborhoodId": 65210556,
      "address": "אפק 27",
      "dealDate": "2022-10-02",
      "dealAmount": 1739000,
      "parcelNum": "4271-132-1",
      "dealNature": "מגורים",
      "roomNum": 0.0,
      "floor": null,
      "assetArea": 0.0,
      "yearBuilt": 0,
      "streetCode": 26400143,
      "settlmentID": 2640,
      "buildingFloors": 0,
      "hokHamecher": 0,
      "trend": {
        "rate": 0,
        "years": 0
      },
      "prevDeals": [],
      "ownership": [],
      "priceSM": 0,
      "row_id": 16
    },
    {
      "assetId": 80007502.0,
      "addressId": 53907527,
      "polygonId": "52333032",
      "neighborhoodName": "שבזי",
      "neighborhoodId": 65210556,
      "address": "ארץ ישראל השלמה 17",
      "dealDate": "2022-09-13",
      "dealAmount": 2500000,
      "parcelNum": "4271-118-2",
      "dealNature": "דירה בבית קומות",
      "roomNum": 5.0,
      "floor": "קומה ‎0‏",
      "assetArea": 108.0,
      "yearBuilt": 1982,
      "streetCode": 26400156,
      "settlmentID": 2640,
      "buildingFloors": 2,
      "hokHamecher": 0,
      "trend": {
        "rate": 0,
        "years": 0
      },
      "prevDeals": [],
      "ownership": [],
      "priceSM": 23148,
      "row_id": 17
    },
    {
      "assetId": 80007517.0,
      "addressId": 53724853,
      "polygonId": "53305376",
      "neighborhoodName": "שבזי",
      "neighborhoodId": 65210556,
      "address": "אחווה 1",
      "dealDate": "2022-04-18",
      "dealAmount": 917000,
      "parcelNum": "4271-123-2",
      "dealNature": "קרקע למגורים",
      "roomNum": 0.0,
      "floor": "ראשונה",
      "assetArea": 21.87,
      "yearBuilt": 1987,
      "streetCode": 26400185,
      "settlmentID": 2640,
      "buildingFloors": 1,
      "hokHamecher": 0,
      "prevDeals": [
        {
          "dealDate": "2005-01-16",
          "dealAmount": 764000
        }
      ],
      "trend": {
        "rate": 20.0,
        "years": 17.3
      },
      "ownership": [],
      "priceSM": 43667,
      "row_id": 18
    },
    {
      "assetId": 80007481.0,
      "addressId": 0,
      "polygonId": "52351229",
      "neighborhoodName": "שבזי",
      "neighborhoodId": 65210556,
      "address": "ארץ ישראל השלמה 4",
      "dealDate": "2022-02-27",
      "dealAmount": 10750000,
      "parcelNum": "4271-112-3",
      "dealNature": "קרקע למגורים",
      "roomNum": 0.0,
      "floor": null,
      "assetArea": 21.87,
      "yearBuilt": 0,
      "streetCode": 26400156,
      "settlmentID": 2640,
      "buildingFloors": 0,
      "hokHamecher": 0,
      "trend": {
        "rate": 0,
        "years": 0
      },
      "prevDeals": [],
      "ownership": [],
      "priceSM": 491541,
      "row_id": 19
    },
    {
      "assetId": 81307699.0,
      "addressId": 53736443,
      "polygonId": "52335443",
      "neighborhoodName": "שבזי",
      "neighborhoodId": 65210556,
      "address": "אפק 29",
      "dealDate": "2021-10-05",
      "dealAmount": 101000,
      "parcelNum": "4271-132-3",
      "dealNature": "דירה בבית קומות",
      "roomNum": 5.0,
      "floor": "ראשונה",
      "assetArea": 163.0,
      "yearBuilt": 1950,
      "streetCode": 26400143,
      "settlmentID": 2640,
      "buildingFloors": 0,
      "hokHamecher": 0,
      "trend": {
        "rate": 0,
        "years": 0
      },
      "prevDeals": [],
      "ownership": [],
      "priceSM": 620,
      "row_id": 20
    },
    {
      "assetId": 4425878.0,
      "addressId": 53727186,
      "polygonId": "52276474",
      "neighborhoodName": "שבזי",
      "neighborhoodId": 65210556,
      "address": "שלמה מעודה 1",
      "dealDate": "2021-07-26",
      "dealAmount": 39640000,
      "parcelNum": "4271-191-2",
      "dealNature": "קרקע למגורים",
      "roomNum": 0.0,
      "floor": null,
      "assetArea": 4133.0,
      "yearBuilt": 2000,
      "streetCode": 26400150,
      "settlmentID": 2640,
      "buildingFloors": 0,
      "hokHamecher": 0,
      "trend": {
        "rate": 0,
        "years": 0
      },
      "prevDeals": [],
      "ownership": [],
      "priceSM": 9591,
      "row_id": 21
    },
    {
      "assetId": 80008122.0,
      "addressId": 71190647,
      "polygonId": "65073597",
      "neighborhoodName": "שבזי",
      "neighborhoodId": 65210556,
      "address": "ג'ון קנדי 4",
      "dealDate": "2021-06-08",
      "dealAmount": 2800000,
      "parcelNum": "4272-93-2",
      "dealNature": "דירה בבית קומות",
      "roomNum": 7.0,
      "floor": "שניה",
      "assetArea": 214.0,
      "yearBuilt": 1993,
      "streetCode": 26400121,
      "settlmentID": 2640,
      "buildingFloors": 0,
      "hokHamecher": 0,
      "prevDeals": [
        {
          "dealDate": "2016-10-27",
          "dealAmount": 2420000
        }
      ],
      "trend": {
        "rate": 15.7,
        "years": 4.6
      },
      "ownership": [],
      "priceSM": 13084,
      "row_id": 22
    },
    {
      "assetId": 4513206.0,
      "addressId": 53732061,
      "polygonId": "53317419",
      "neighborhoodName": "שבזי",
      "neighborhoodId": 65210556,
      "address": "יהודה הלוי 160",
      "dealDate": "2021-05-27",
      "dealAmount": 3560000,
      "parcelNum": "4270-103-1",
      "dealNature": "קרקע למגורים",
      "roomNum": 0.0,
      "floor": null,
      "assetArea": 730.0,
      "yearBuilt": 0,
      "streetCode": 26400125,
      "settlmentID": 2640,
      "buildingFloors": 0,
      "hokHamecher": 0,
      "trend": {
        "rate": 0,
        "years": 0
      },
      "prevDeals": [],
      "ownership": [],
      "priceSM": 4877,
      "row_id": 23
    },
    {
      "assetId": 80007449.0,
      "addressId": 53733577,
      "polygonId": "52241808",
      "neighborhoodName": "שבזי",
      "neighborhoodId": 65210556,
      "address": "אפק 12",
      "dealDate": "2021-05-05",
      "dealAmount": 2550000,
      "parcelNum": "4271-105-2",
      "dealNature": "קרקע למגורים",
      "roomNum": 0.0,
      "floor": null,
      "assetArea": 50.3,
      "yearBuilt": 2004,
      "streetCode": 26400143,
      "settlmentID": 2640,
      "buildingFloors": 0,
      "hokHamecher": 0,
      "trend": {
        "rate": 0,
        "years": 0
      },
      "prevDeals": [],
      "ownership": [],
      "priceSM": 50696,
      "row_id": 24
    },
    {
      "assetId": 80007402.0,
      "addressId": 53908201,
      "polygonId": "52299710",
      "neighborhoodName": "שבזי",
      "neighborhoodId": 65210556,
      "address": "אפק 60",
      "dealDate": "2021-03-11",
      "dealAmount": 161000,
      "parcelNum": "4271-93-2",
      "dealNature": "דירה בבית קומות",
      "roomNum": 2.0,
      "floor": "ראשונה",
      "assetArea": 21.87,
      "yearBuilt": 1950,
      "streetCode": 26400143,
      "settlmentID": 2640,
      "buildingFloors": 0,
      "hokHamecher": 0,
      "prevDeals": [
        {
          "dealDate": "2020-12-16",
          "dealAmount": 161000
        },
        {
          "dealDate": "2018-09-17",
          "dealAmount": 161000
        }
      ],
      "trend": {
        "rate": 0.0,
        "years": 0.2
      },
      "ownership": [],
      "priceSM": 7667,
      "row_id": 25
    },
    {
      "assetId": 81307699.0,
      "addressId": 53727292,
      "polygonId": "52335443",
      "neighborhoodName": "שבזי",
      "neighborhoodId": 65210556,
      "address": "אפק 27",
      "dealDate": "2021-01-13",
      "dealAmount": 836000,
      "parcelNum": "4271-132-6",
      "dealNature": "מגורים",
      "roomNum": 0.0,
      "floor": null,
      "assetArea": 240.0,
      "yearBuilt": 0,
      "streetCode": 26400143,
      "settlmentID": 2640,
      "buildingFloors": 0,
      "hokHamecher": 0,
      "trend": {
        "rate": 0,
        "years": 0
      },
      "prevDeals": [],
      "ownership": [],
      "priceSM": 3483,
      "row_id": 28
    },
    {
      "assetId": 81307699.0,
      "addressId": 53727292,
      "polygonId": "52335443",
      "neighborhoodName": "שבזי",
      "neighborhoodId": 65210556,
      "address": "אפק 27",
      "dealDate": "2020-11-02",
      "dealAmount": 800000,
      "parcelNum": "4271-132-7",
      "dealNature": "דירה בבית קומות",
      "roomNum": 3.0,
      "floor": "שניה",
      "assetArea": 85.0,
      "yearBuilt": 1970,
      "streetCode": 26400143,
      "settlmentID": 2640,
      "buildingFloors": 0,
      "hokHamecher": 0,
      "trend": {
        "rate": 0,
        "years": 0
      },
      "prevDeals": [],
      "ownership": [],
      "priceSM": 9412,
      "row_id": 29
    },
    {
      "assetId": 81307699.0,
      "addressId": 53727292,
      "polygonId": "52335443",
      "neighborhoodName": "שבזי",
      "neighborhoodId": 65210556,
      "address": "אפק 27",
      "dealDate": "2020-11-01",
      "dealAmount": 400000,
      "parcelNum": "4271-132-8",
      "dealNature": "מגורים",
      "roomNum": 0.0,
      "floor": null,
      "assetArea": 0.0,
      "yearBuilt": 0,
      "streetCode": 26400143,
      "settlmentID": 2640,
      "buildingFloors": 0,
      "hokHamecher": 0,
      "trend": {
        "rate": 0,
        "years": 0
      },
      "prevDeals": [],
      "ownership": [],
      "priceSM": 0,
      "row_id": 30
    },
    {
      "assetId": 4092352.0,
      "addressId": 0,
      "polygonId": "4272-37",
      "neighborhoodName": "שבזי",
      "neighborhoodId": 65210556,
      "address": "0",
      "dealDate": "2020-10-01",
      "dealAmount": 1050000,
      "parcelNum": "4272-37-1",
      "dealNature": "מגורים",
      "roomNum": 0.0,
      "floor": null,
      "assetArea": 234.0,
      "yearBuilt": 0,
      "streetCode": 0,
      "settlmentID": 2640,
      "buildingFloors": 0,
      "hokHamecher": 0,
      "trend": {
        "rate": 0,
        "years": 0
      },
      "prevDeals": [],
      "ownership": [],
      "priceSM": 4487,
      "row_id": 32
    },
    {
      "assetId": 80007579.0,
      "addressId": 53908740,
      "polygonId": "53425708",
      "neighborhoodName": "שבזי",
      "neighborhoodId": 65210556,
      "address": "יורם חתוכה 15",
      "dealDate": "2020-07-31",
      "dealAmount": 760000,
      "parcelNum": "4271-141-1",
      "dealNature": "קרקע למגורים",
      "roomNum": 0.0,
      "floor": null,
      "assetArea": 39.0,
      "yearBuilt": 0,
      "streetCode": 26400186,
      "settlmentID": 2640,
      "buildingFloors": 0,
      "hokHamecher": 0,
      "trend": {
        "rate": 0,
        "years": 0
      },
      "prevDeals": [],
      "ownership": [],
      "priceSM": 19487,
      "row_id": 33
    },
    {
      "assetId": 4092352.0,
      "addressId": 0,
      "polygonId": "4272-37",
      "neighborhoodName": "שבזי",
      "neighborhoodId": 65210556,
      "address": "0",
      "dealDate": "2020-07-03",
      "dealAmount": 550000,
      "parcelNum": "4272-37-2",
      "dealNature": "מגורים",
      "roomNum": 0.0,
      "floor": null,
      "assetArea": 221.0,
      "yearBuilt": 0,
      "streetCode": 0,
      "settlmentID": 2640,
      "buildingFloors": 0,
      "hokHamecher": 0,
      "trend": {
        "rate": 0,
        "years": 0
      },
      "prevDeals": [],
      "ownership": [],
      "priceSM": 2489,
      "row_id": 34
    },
    {
      "assetId": 81307699.0,
      "addressId": 53727292,
      "polygonId": "52335443",
      "neighborhoodName": "שבזי",
      "neighborhoodId": 65210556,
      "address": "אפק 27",
      "dealDate": "2020-06-04",
      "dealAmount": 4650000,
      "parcelNum": "4271-132-9",
      "dealNature": "מגורים",
      "roomNum": 0.0,
      "floor": null,
      "assetArea": 964.0,
      "yearBuilt": 0,
      "streetCode": 26400143,
      "settlmentID": 2640,
      "buildingFloors": 0,
      "hokHamecher": 0,
      "trend": {
        "rate": 0,
        "years": 0
      },
      "prevDeals": [],
      "ownership": [],
      "priceSM": 4824,
      "row_id": 35
    },
    {
      "assetId": 80006875.0,
      "addressId": 53732148,
      "polygonId": "52340625",
      "neighborhoodName": "שבזי",
      "neighborhoodId": 65210556,
      "address": "אפק 70",
      "dealDate": "2020-05-18",
      "dealAmount": 1500000,
      "parcelNum": "4270-56-1",
      "dealNature": "דירה בבית קומות",
      "roomNum": 3.0,
      "floor": "ראשונה",
      "assetArea": 70.0,
      "yearBuilt": 1970,
      "streetCode": 26400143,
      "settlmentID": 2640,
      "buildingFloors": 0,
      "hokHamecher": 0,
      "trend": {
        "rate": 0,
        "years": 0
      },
      "prevDeals": [],
      "ownership": [],
      "priceSM": 21429,
      "row_id": 36
    },
    {
      "assetId": 80924411.0,
      "addressId": 0,
      "polygonId": "4270-187",
      "neighborhoodName": "שבזי",
      "neighborhoodId": 65210556,
      "address": "0",
      "dealDate": "2020-03-16",
      "dealAmount": 749000,
      "parcelNum": "4270-187-1",
      "dealNature": "קוטג' דו משפחתי",
      "roomNum": 7.0,
      "floor": null,
      "assetArea": 196.0,
      "yearBuilt": 0,
      "streetCode": 0,
      "settlmentID": 2640,
      "buildingFloors": 0,
      "hokHamecher": 0,
      "trend": {
        "rate": 0,
        "years": 0
      },
      "prevDeals": [],
      "ownership": [],
      "priceSM": 3821,
      "row_id": 37
    },
    {
      "assetId": 80006869.0,
      "addressId": 53733824,
      "polygonId": "52284773",
      "neighborhoodName": "שבזי",
      "neighborhoodId": 65210556,
      "address": "אפק 78",
      "dealDate": "2019-09-22",
      "dealAmount": 1950000,
      "parcelNum": "4270-54-1",
      "dealNature": "קוטג' חד משפחתי",
      "roomNum": 5.5,
      "floor": "קומה ‎0‏",
      "assetArea": 175.0,
      "yearBuilt": 1970,
      "streetCode": 26400143,
      "settlmentID": 2640,
      "buildingFloors": 2,
      "hokHamecher": 0,
      "trend": {
        "rate": 0,
        "years": 0
      },
      "prevDeals": [],
      "ownership": [],
      "priceSM": 11143,
      "row_id": 38
    },
    {
      "assetId": 80400841.0,
      "addressId": 53732563,
      "polygonId": "52335912",
      "neighborhoodName": "שבזי",
      "neighborhoodId": 65210556,
      "address": "אפק 82",
      "dealDate": "2019-07-28",
      "dealAmount": 1150000,
      "parcelNum": "4270-53-5",
      "dealNature": "קרקע למגורים",
      "roomNum": 0.0,
      "floor": "קרקע",
      "assetArea": 39.3,
      "yearBuilt": 1970,
      "streetCode": 26400143,
      "settlmentID": 2640,
      "buildingFloors": 0,
      "hokHamecher": 0,
      "prevDeals": [
        {
          "dealDate": "2019-07-22",
          "dealAmount": 1050000
        },
        {
          "dealDate": "2018-07-29",
          "dealAmount": 750000
        },
        {
          "dealDate": "2017-11-14",
          "dealAmount": 1040000
        },
        {
          "dealDate": "2017-09-11",
          "dealAmount": 1230000
        }
      ],
      "trend": {
        "rate": 9.5,
        "years": 0.0
      },
      "ownership": [],
      "priceSM": 29487,
      "row_id": 39
    },
    {
      "assetId": 80008434.0,
      "addressId": 53720064,
      "polygonId": "52286064",
      "neighborhoodName": "שבזי",
      "neighborhoodId": 65210556,
      "address": "המעפיל 19",
      "dealDate": "2019-07-17",
      "dealAmount": 900000,
      "parcelNum": "4272-230-1",
      "dealNature": "דירה בבית קומות",
      "roomNum": 3.0,
      "floor": "רביעית",
      "assetArea": 65.0,
      "yearBuilt": 1970,
      "streetCode": 26400198,
      "settlmentID": 2640,
      "buildingFloors": 0,
      "hokHamecher": 0,
      "trend": {
        "rate": 0,
        "years": 0
      },
      "prevDeals": [],
      "ownership": [],
      "priceSM": 13846,
      "row_id": 40
    },
    {
      "assetId": 4431318.0,
      "addressId": 53737927,
      "polygonId": "52300694",
      "neighborhoodName": "שבזי",
      "neighborhoodId": 65210556,
      "address": "אפק 91",
      "dealDate": "2019-06-23",
      "dealAmount": 480000,
      "parcelNum": "4270-114-1",
      "dealNature": "דירה בבית קומות",
      "roomNum": 7.0,
      "floor": null,
      "assetArea": 116.0,
      "yearBuilt": 1960,
      "streetCode": 26400143,
      "settlmentID": 2640,
      "buildingFloors": 0,
      "hokHamecher": 0,
      "trend": {
        "rate": 0,
        "years": 0
      },
      "prevDeals": [],
      "ownership": [],
      "priceSM": 4138,
      "row_id": 41
    },
    {
      "assetId": 80006872.0,
      "addressId": 53908103,
      "polygonId": "52188761",
      "neighborhoodName": "שבזי",
      "neighborhoodId": 65210556,
      "address": "אפק 74",
      "dealDate": "2019-06-12",
      "dealAmount": 1350000,
      "parcelNum": "4270-55-1",
      "dealNature": "קרקע למגורים",
      "roomNum": 0.0,
      "floor": null,
      "assetArea": 32.85,
      "yearBuilt": 0,
      "streetCode": 26400143,
      "settlmentID": 2640,
      "buildingFloors": 0,
      "hokHamecher": 0,
      "trend": {
        "rate": 0,
        "years": 0
      },
      "prevDeals": [],
      "ownership": [],
      "priceSM": 41096,
      "row_id": 42
    },
    {
      "assetId": 80007438.0,
      "addressId": 53907518,
      "polygonId": "53292489",
      "neighborhoodName": "שבזי",
      "neighborhoodId": 65210556,
      "address": "אפק 22",
      "dealDate": "2019-05-30",
      "dealAmount": 830000,
      "parcelNum": "4271-102-1",
      "dealNature": "קרקע למגורים",
      "roomNum": 0.0,
      "floor": null,
      "assetArea": 29.62,
      "yearBuilt": 0,
      "streetCode": 26400143,
      "settlmentID": 2640,
      "buildingFloors": 0,
      "hokHamecher": 0,
      "trend": {
        "rate": 0,
        "years": 0
      },
      "prevDeals": [],
      "ownership": [],
      "priceSM": 28022,
      "row_id": 43
    },
    {
      "assetId": 80007564.0,
      "addressId": 53731176,
      "polygonId": "53285824",
      "neighborhoodName": "שבזי",
      "neighborhoodId": 65210556,
      "address": "יורם חתוכה 22",
      "dealDate": "2019-05-05",
      "dealAmount": 2020000,
      "parcelNum": "4271-136-2",
      "dealNature": "קוטג' דו משפחתי",
      "roomNum": 5.0,
      "floor": null,
      "assetArea": 163.0,
      "yearBuilt": 1991,
      "streetCode": 26400186,
      "settlmentID": 2640,
      "buildingFloors": 0,
      "hokHamecher": 0,
      "trend": {
        "rate": 0,
        "years": 0
      },
      "prevDeals": [],
      "ownership": [],
      "priceSM": 12393,
      "row_id": 44
    },
    {
      "assetId": 80007065.0,
      "addressId": 53733867,
      "polygonId": "52321316",
      "neighborhoodName": "שבזי",
      "neighborhoodId": 65210556,
      "address": "אפק 126",
      "dealDate": "2019-04-30",
      "dealAmount": 1370000,
      "parcelNum": "4270-121-1",
      "dealNature": "קרקע למגורים",
      "roomNum": 0.0,
      "floor": "קרקע",
      "assetArea": 22.1,
      "yearBuilt": 0,
      "streetCode": 26400143,
      "settlmentID": 2640,
      "buildingFloors": 0,
      "hokHamecher": 0,
      "trend": {
        "rate": 0,
        "years": 0
      },
      "prevDeals": [],
      "ownership": [],
      "priceSM": 61991,
      "row_id": 45
    },
    {
      "assetId": 4092352.0,
      "addressId": 0,
      "polygonId": "4272-37",
      "neighborhoodName": "שבזי",
      "neighborhoodId": 65210556,
      "address": "0",
      "dealDate": "2019-04-18",
      "dealAmount": 700000,
      "parcelNum": "4272-37-3",
      "dealNature": "קוטג' חד משפחתי",
      "roomNum": 3.0,
      "floor": null,
      "assetArea": 64.0,
      "yearBuilt": 0,
      "streetCode": 0,
      "settlmentID": 2640,
      "buildingFloors": 0,
      "hokHamecher": 0,
      "trend": {
        "rate": 0,
        "years": 0
      },
      "prevDeals": [],
      "ownership": [],
      "priceSM": 10938,
      "row_id": 46
    },
    {
      "assetId": 80006868.0,
      "addressId": 53733824,
      "polygonId": "52284773",
      "neighborhoodName": "שבזי",
      "neighborhoodId": 65210556,
      "address": "אפק 78",
      "dealDate": "2018-07-03",
      "dealAmount": 1010000,
      "parcelNum": "4270-54-0",
      "dealNature": "קרקע למגורים",
      "roomNum": 0.0,
      "floor": "ראשונה",
      "assetArea": 3001.0,
      "yearBuilt": 1970,
      "streetCode": 26400143,
      "settlmentID": 2640,
      "buildingFloors": 2,
      "hokHamecher": 0,
      "prevDeals": [
        {
          "dealDate": "2007-03-22",
          "dealAmount": 377000
        }
      ],
      "trend": {
        "rate": 167.9,
        "years": 11.3
      },
      "ownership": [],
      "priceSM": 337,
      "row_id": 47
    },
    {
      "assetId": 80007559.0,
      "addressId": 53724964,
      "polygonId": "52191588",
      "neighborhoodName": "שבזי",
      "neighborhoodId": 65210556,
      "address": "יורם חתוכה 20",
      "dealDate": "2018-05-07",
      "dealAmount": 2300000,
      "parcelNum": "4271-135-0",
      "dealNature": "קוטג' דו משפחתי",
      "roomNum": 7.0,
      "floor": null,
      "assetArea": 225.0,
      "yearBuilt": 2000,
      "streetCode": 26400186,
      "settlmentID": 2640,
      "buildingFloors": 0,
      "hokHamecher": 0,
      "trend": {
        "rate": 0,
        "years": 0
      },
      "prevDeals": [],
      "ownership": [],
      "priceSM": 10222,
      "row_id": 48
    },
    {
      "assetId": 4090930.0,
      "addressId": 0,
      "polygonId": "4270-155",
      "neighborhoodName": "שבזי",
      "neighborhoodId": 65210556,
      "address": "0",
      "dealDate": "2018-01-14",
      "dealAmount": 750000,
      "parcelNum": "4270-155-1",
      "dealNature": "קוטג' חד משפחתי",
      "roomNum": 7.0,
      "floor": null,
      "assetArea": 196.0,
      "yearBuilt": 0,
      "streetCode": 0,
      "settlmentID": 2640,
      "buildingFloors": 0,
      "hokHamecher": 0,
      "trend": {
        "rate": 0,
        "years": 0
      },
      "prevDeals": [],
      "ownership": [],
      "priceSM": 3827,
      "row_id": 49
    },
    {
      "assetId": 80006925.0,
      "addressId": 53728780,
      "polygonId": "71177236",
      "neighborhoodName": "שבזי",
      "neighborhoodId": 65210556,
      "address": "שבזי 112",
      "dealDate": "2017-08-22",
      "dealAmount": 1500000,
      "parcelNum": "4270-69-3",
      "dealNature": "קוטג' חד משפחתי",
      "roomNum": 3.0,
      "floor": null,
      "assetArea": 100.0,
      "yearBuilt": 1970,
      "streetCode": 26400142,
      "settlmentID": 2640,
      "buildingFloors": 0,
      "hokHamecher": 0,
      "prevDeals": [
        {
          "dealDate": "2003-04-16",
          "dealAmount": 824000
        }
      ],
      "trend": {
        "rate": 82.0,
        "years": 14.4
      },
      "ownership": [],
      "priceSM": 15000,
      "row_id": 50
    },
    {
      "assetId": 80006898.0,
      "addressId": 71190575,
      "polygonId": "52380376",
      "neighborhoodName": "שבזי",
      "neighborhoodId": 65210556,
      "address": "יורם חתוכה 46",
      "dealDate": "2017-06-26",
      "dealAmount": 2200000,
      "parcelNum": "4270-61-5",
      "dealNature": "דירה בבית קומות",
      "roomNum": 6.0,
      "floor": "קרקע+ראשונה",
      "assetArea": 149.6,
      "yearBuilt": 1990,
      "streetCode": 26400186,
      "settlmentID": 2640,
      "buildingFloors": 2,
      "hokHamecher": 0,
      "prevDeals": [
        {
          "dealDate": "2006-06-08",
          "dealAmount": 915000
        }
      ],
      "trend": {
        "rate": 140.4,
        "years": 11.1
      },
      "ownership": [],
      "priceSM": 14765,
      "row_id": 51
    },
    {
      "assetId": 80008166.0,
      "addressId": 53738505,
      "polygonId": "52352785",
      "neighborhoodName": "שבזי",
      "neighborhoodId": 65210556,
      "address": "שבזי 113",
      "dealDate": "2017-06-05",
      "dealAmount": 1900000,
      "parcelNum": "4272-104-1",
      "dealNature": "קוטג' טורי",
      "roomNum": 4.0,
      "floor": "ראשונה",
      "assetArea": 75.77,
      "yearBuilt": 1957,
      "streetCode": 26400142,
      "settlmentID": 2640,
      "buildingFloors": 1,
      "hokHamecher": 0,
      "trend": {
        "rate": 0,
        "years": 0
      },
      "prevDeals": [],
      "ownership": [],
      "priceSM": 25076,
      "row_id": 52
    },
    {
      "assetId": 80007461.0,
      "addressId": 53841443,
      "polygonId": "52239386",
      "neighborhoodName": "שבזי",
      "neighborhoodId": 65210556,
      "address": "אצ\"ל 3",
      "dealDate": "2017-04-06",
      "dealAmount": 2100000,
      "parcelNum": "4271-107-4",
      "dealNature": "קוטג' דו משפחתי",
      "roomNum": 6.0,
      "floor": "קרקע+ראשונה",
      "assetArea": 177.1,
      "yearBuilt": 1995,
      "streetCode": 26400184,
      "settlmentID": 2640,
      "buildingFloors": 0,
      "hokHamecher": 0,
      "trend": {
        "rate": 0,
        "years": 0
      },
      "prevDeals": [],
      "ownership": [],
      "priceSM": 11858,
      "row_id": 53
    },
    {
      "assetId": 80007039.0,
      "addressId": 53735136,
      "polygonId": "53301764",
      "neighborhoodName": "שבזי",
      "neighborhoodId": 65210556,
      "address": "יהודה הלוי 176",
      "dealDate": "2016-09-27",
      "dealAmount": 1220000,
      "parcelNum": "4270-111-0",
      "dealNature": "קוטג' חד משפחתי",
      "roomNum": 1.5,
      "floor": null,
      "assetArea": 1533.0,
      "yearBuilt": 1950,
      "streetCode": 26400125,
      "settlmentID": 2640,
      "buildingFloors": 0,
      "hokHamecher": 0,
      "trend": {
        "rate": 0,
        "years": 0
      },
      "prevDeals": [],
      "ownership": [],
      "priceSM": 796,
      "row_id": 54
    },
    {
      "assetId": 80006876.0,
      "addressId": 53733040,
      "polygonId": "53290021",
      "neighborhoodName": "שבזי",
      "neighborhoodId": 65210556,
      "address": "אצ\"ל 71",
      "dealDate": "2016-04-06",
      "dealAmount": 1750000,
      "parcelNum": "4270-56-2",
      "dealNature": "קוטג' דו משפחתי",
      "roomNum": 4.0,
      "floor": "ראשונה",
      "assetArea": 100.0,
      "yearBuilt": 1970,
      "streetCode": 26400184,
      "settlmentID": 2640,
      "buildingFloors": 0,
      "hokHamecher": 0,
      "trend": {
        "rate": 0,
        "years": 0
      },
      "prevDeals": [],
      "ownership": [],
      "priceSM": 17500,
      "row_id": 55
    },
    {
      "assetId": 80006866.0,
      "addressId": 53732563,
      "polygonId": "52335912",
      "neighborhoodName": "שבזי",
      "neighborhoodId": 65210556,
      "address": "אפק 82",
      "dealDate": "2015-09-01",
      "dealAmount": 749000,
      "parcelNum": "4270-53-1",
      "dealNature": "דירת גן",
      "roomNum": 3.0,
      "floor": "קרקע",
      "assetArea": 81.4,
      "yearBuilt": 1970,
      "streetCode": 26400143,
      "settlmentID": 2640,
      "buildingFloors": 0,
      "hokHamecher": 0,
      "trend": {
        "rate": 0,
        "years": 0
      },
      "prevDeals": [],
      "ownership": [],
      "priceSM": 9201,
      "row_id": 56
    },
    {
      "assetId": 80007436.0,
      "addressId": 71190598,
      "polygonId": "52335462",
      "neighborhoodName": "שבזי",
      "neighborhoodId": 65210556,
      "address": "אצ\"ל 27",
      "dealDate": "2015-06-23",
      "dealAmount": 1549000,
      "parcelNum": "4271-101-7",
      "dealNature": "דירה בבית קומות",
      "roomNum": 4.0,
      "floor": null,
      "assetArea": 100.0,
      "yearBuilt": 2015,
      "streetCode": 26400184,
      "settlmentID": 2640,
      "buildingFloors": 1,
      "hokHamecher": 0,
      "trend": {
        "rate": 0,
        "years": 0
      },
      "prevDeals": [],
      "ownership": [],
      "priceSM": 15490,
      "row_id": 57
    },
    {
      "assetId": 80007516.0,
      "addressId": 53908717,
      "polygonId": "71177214",
      "neighborhoodName": "שבזי",
      "neighborhoodId": 65210556,
      "address": "אחווה 3",
      "dealDate": "2015-04-15",
      "dealAmount": 2000000,
      "parcelNum": "4271-123-1",
      "dealNature": "קוטג' חד משפחתי",
      "roomNum": 6.0,
      "floor": "ראשונה",
      "assetArea": 187.0,
      "yearBuilt": 1987,
      "streetCode": 26400185,
      "settlmentID": 2640,
      "buildingFloors": 1,
      "hokHamecher": 0,
      "trend": {
        "rate": 0,
        "years": 0
      },
      "prevDeals": [],
      "ownership": [],
      "priceSM": 10695,
      "row_id": 58
    },
    {
      "assetId": 80007436.0,
      "addressId": 71190598,
      "polygonId": "52335462",
      "neighborhoodName": "שבזי",
      "neighborhoodId": 65210556,
      "address": "אצ\"ל 27",
      "dealDate": "2015-03-15",
      "dealAmount": 1315000,
      "parcelNum": "4271-101-8",
      "dealNature": "דירה בבית קומות",
      "roomNum": 4.0,
      "floor": "שמינית",
      "assetArea": 114.0,
      "yearBuilt": 2015,
      "streetCode": 26400184,
      "settlmentID": 2640,
      "buildingFloors": 1,
      "hokHamecher": 0,
      "trend": {
        "rate": 0,
        "years": 0
      },
      "prevDeals": [],
      "ownership": [],
      "priceSM": 11535,
      "row_id": 59
    },
    {
      "assetId": 80007436.0,
      "addressId": 71190598,
      "polygonId": "52335462",
      "neighborhoodName": "שבזי",
      "neighborhoodId": 65210556,
      "address": "אצ\"ל 27",
      "dealDate": "2015-03-11",
      "dealAmount": 1330000,
      "parcelNum": "4271-101-9",
      "dealNature": "דירה בבית קומות",
      "roomNum": 4.0,
      "floor": "שביעית",
      "assetArea": 100.0,
      "yearBuilt": 2015,
      "streetCode": 26400184,
      "settlmentID": 2640,
      "buildingFloors": 1,
      "hokHamecher": 0,
      "trend": {
        "rate": 0,
        "years": 0
      },
      "prevDeals": [],
      "ownership": [],
      "priceSM": 13300,
      "row_id": 60
    },
    {
      "assetId": 7000110.0,
      "addressId": 53841443,
      "polygonId": "52239386",
      "neighborhoodName": "שבזי",
      "neighborhoodId": 65210556,
      "address": "אצ\"ל 3",
      "dealDate": "2014-08-12",
      "dealAmount": 1280000,
      "parcelNum": "4271-107-6",
      "dealNature": "דירה",
      "roomNum": 4.0,
      "floor": "תשיעית",
      "assetArea": 107.0,
      "yearBuilt": 1995,
      "streetCode": 26400184,
      "settlmentID": 2640,
      "buildingFloors": 0,
      "hokHamecher": 1,
      "trend": {
        "rate": 0,
        "years": 0
      },
      "prevDeals": [],
      "ownership": [],
      "priceSM": 11963,
      "row_id": 61
    },
    {
      "assetId": 7000111.0,
      "addressId": 53841443,
      "polygonId": "52239386",
      "neighborhoodName": "שבזי",
      "neighborhoodId": 65210556,
      "address": "אצ\"ל 3",
      "dealDate": "2014-01-14",
      "dealAmount": 1280000,
      "parcelNum": "4271-107-7",
      "dealNature": "דירה",
      "roomNum": 4.0,
      "floor": "שמינית",
      "assetArea": 107.0,
      "yearBuilt": 1995,
      "streetCode": 26400184,
      "settlmentID": 2640,
      "buildingFloors": 0,
      "hokHamecher": 1,
      "trend": {
        "rate": 0,
        "years": 0
      },
      "prevDeals": [],
      "ownership": [],
      "priceSM": 11963,
      "row_id": 62
    },
    {
      "assetId": 7000111.0,
      "addressId": 53841443,
      "polygonId": "52239386",
      "neighborhoodName": "שבזי",
      "neighborhoodId": 65210556,
      "address": "אצ\"ל 3",
      "dealDate": "2012-12-24",
      "dealAmount": 1360000,
      "parcelNum": "4271-107-8",
      "dealNature": "דירה בבית קומות",
      "roomNum": 4.0,
      "floor": "שישית",
      "assetArea": 127.0,
      "yearBuilt": 1995,
      "streetCode": 26400184,
      "settlmentID": 2640,
      "buildingFloors": 0,
      "hokHamecher": 0,
      "prevDeals": [
        {
          "dealDate": "2012-12-24",
          "dealAmount": 1380000
        }
      ],
      "trend": {
        "rate": -1.4,
        "years": 0.0
      },
      "ownership": [],
      "priceSM": 10709,
      "row_id": 63
    },
    {
      "assetId": 80006921.0,
      "addressId": 53733834,
      "polygonId": "71177206",
      "neighborhoodName": "שבזי",
      "neighborhoodId": 65210556,
      "address": "שבזי 116",
      "dealDate": "2011-01-11",
      "dealAmount": 1250000,
      "parcelNum": "4270-68-2",
      "dealNature": "דירה בבית קומות",
      "roomNum": 4.5,
      "floor": "ראשונה",
      "assetArea": 40.36,
      "yearBuilt": 2003,
      "streetCode": 26400142,
      "settlmentID": 2640,
      "buildingFloors": 1,
      "hokHamecher": 0,
      "prevDeals": [
        {
          "dealDate": "1999-12-30",
          "dealAmount": 730000
        }
      ],
      "trend": {
        "rate": 71.2,
        "years": 11.0
      },
      "ownership": [],
      "priceSM": 31250,
      "row_id": 64
    },
    {
      "assetId": 4092338.0,
      "addressId": 0,
      "polygonId": "4271-178",
      "neighborhoodName": "שבזי",
      "neighborhoodId": 65210556,
      "address": "0",
      "dealDate": "2010-01-10",
      "dealAmount": 1120000,
      "parcelNum": "4271-178-1",
      "dealNature": "דירה",
      "roomNum": 4.0,
      "floor": "שמינית",
      "assetArea": 107.0,
      "yearBuilt": 0,
      "streetCode": 0,
      "settlmentID": 2640,
      "buildingFloors": 0,
      "hokHamecher": 1,
      "trend": {
        "rate": 0,
        "years": 0
      },
      "prevDeals": [],
      "ownership": [],
      "priceSM": 10467,
      "row_id": 65
    },
    {
      "assetId": 80008155.0,
      "addressId": 0,
      "polygonId": "52348863",
      "neighborhoodName": "שבזי",
      "neighborhoodId": 65210556,
      "address": "המעפיל 7",
      "dealDate": "2008-10-12",
      "dealAmount": 920000,
      "parcelNum": "4272-101-2",
      "dealNature": "בית בודד",
      "roomNum": 3.0,
      "floor": null,
      "assetArea": 70.0,
      "yearBuilt": 1965,
      "streetCode": 26400198,
      "settlmentID": 2640,
      "buildingFloors": 0,
      "hokHamecher": 0,
      "trend": {
        "rate": 0,
        "years": 0
      },
      "prevDeals": [],
      "ownership": [],
      "priceSM": 13143,
      "row_id": 66
    },
    {
      "assetId": 80007044.0,
      "addressId": 53726914,
      "polygonId": "71177208",
      "neighborhoodName": "שבזי",
      "neighborhoodId": 65210556,
      "address": "יהודה הלוי 180",
      "dealDate": "2008-09-21",
      "dealAmount": 200000,
      "parcelNum": "4270-112-2",
      "dealNature": "בית בודד",
      "roomNum": 2.5,
      "floor": "קרקע",
      "assetArea": 29.25,
      "yearBuilt": 1975,
      "streetCode": 26400125,
      "settlmentID": 2640,
      "buildingFloors": 0,
      "hokHamecher": 0,
      "trend": {
        "rate": 0,
        "years": 0
      },
      "prevDeals": [],
      "ownership": [],
      "priceSM": 6838,
      "row_id": 67
    },
    {
      "assetId": 80007449.0,
      "addressId": 53735414,
      "polygonId": "53295038",
      "neighborhoodName": "שבזי",
      "neighborhoodId": 65210556,
      "address": "אפק 10",
      "dealDate": "2008-08-12",
      "dealAmount": 850000,
      "parcelNum": "4271-105-3",
      "dealNature": "דירה בבית קומות",
      "roomNum": 4.0,
      "floor": "ראשונה",
      "assetArea": 100.0,
      "yearBuilt": 2004,
      "streetCode": 26400143,
      "settlmentID": 2640,
      "buildingFloors": 0,
      "hokHamecher": 0,
      "trend": {
        "rate": 0,
        "years": 0
      },
      "prevDeals": [],
      "ownership": [],
      "priceSM": 8500,
      "row_id": 68
    },
    {
      "assetId": 80007043.0,
      "addressId": 53726914,
      "polygonId": "71177208",
      "neighborhoodName": "שבזי",
      "neighborhoodId": 65210556,
      "address": "יהודה הלוי 180",
      "dealDate": "2008-03-17",
      "dealAmount": 1155000,
      "parcelNum": "4270-112-1",
      "dealNature": "בית בודד",
      "roomNum": 5.0,
      "floor": "קרקע",
      "assetArea": 86.25,
      "yearBuilt": 1975,
      "streetCode": 26400125,
      "settlmentID": 2640,
      "buildingFloors": 0,
      "hokHamecher": 0,
      "trend": {
        "rate": 0,
        "years": 0
      },
      "prevDeals": [],
      "ownership": [],
      "priceSM": 13391,
      "row_id": 69
    },
    {
      "assetId": 80006900.0,
      "addressId": 53727184,
      "polygonId": "52323617",
      "neighborhoodName": "שבזי",
      "neighborhoodId": 65210556,
      "address": "אפק 71",
      "dealDate": "2007-12-02",
      "dealAmount": 194000,
      "parcelNum": "4270-62-0",
      "dealNature": "קרקע למגורים",
      "roomNum": 0.0,
      "floor": null,
      "assetArea": 2923.0,
      "yearBuilt": 0,
      "streetCode": 26400143,
      "settlmentID": 2640,
      "buildingFloors": 0,
      "hokHamecher": 0,
      "trend": {
        "rate": 0,
        "years": 0
      },
      "prevDeals": [],
      "ownership": [],
      "priceSM": 66,
      "row_id": 70
    },
    {
      "assetId": 80007475.0,
      "addressId": 53908778,
      "polygonId": "53303048",
      "neighborhoodName": "שבזי",
      "neighborhoodId": 65210556,
      "address": "ארץ ישראל השלמה 10",
      "dealDate": "2007-10-09",
      "dealAmount": 711000,
      "parcelNum": "4271-111-0",
      "dealNature": "קרקע למגורים",
      "roomNum": 0.0,
      "floor": null,
      "assetArea": 3008.0,
      "yearBuilt": 1960,
      "streetCode": 26400156,
      "settlmentID": 2640,
      "buildingFloors": 0,
      "hokHamecher": 0,
      "trend": {
        "rate": 0,
        "years": 0
      },
      "prevDeals": [],
      "ownership": [],
      "priceSM": 236,
      "row_id": 71
    },
    {
      "assetId": 4090930.0,
      "addressId": 0,
      "polygonId": "4270-155",
      "neighborhoodName": "שבזי",
      "neighborhoodId": 65210556,
      "address": "0",
      "dealDate": "2007-05-17",
      "dealAmount": 951000,
      "parcelNum": "4270-155-2",
      "dealNature": "דירה בבית קומות",
      "roomNum": 5.0,
      "floor": null,
      "assetArea": 278.0,
      "yearBuilt": 0,
      "streetCode": 0,
      "settlmentID": 2640,
      "buildingFloors": 0,
      "hokHamecher": 0,
      "trend": {
        "rate": 0,
        "years": 0
      },
      "prevDeals": [],
      "ownership": [],
      "priceSM": 3421,
      "row_id": 73
    },
    {
      "assetId": 80006985.0,
      "addressId": 53774434,
      "polygonId": "52335453",
      "neighborhoodName": "שבזי",
      "neighborhoodId": 65210556,
      "address": "יהודה הלוי 142",
      "dealDate": "2007-01-15",
      "dealAmount": 760000,
      "parcelNum": "4270-93-2",
      "dealNature": "בית בודד",
      "roomNum": 4.0,
      "floor": "קרקע",
      "assetArea": 107.0,
      "yearBuilt": 1970,
      "streetCode": 26400125,
      "settlmentID": 2640,
      "buildingFloors": 0,
      "hokHamecher": 0,
      "prevDeals": [
        {
          "dealDate": "2000-03-08",
          "dealAmount": 722000
        }
      ],
      "trend": {
        "rate": 5.3,
        "years": 6.9
      },
      "ownership": [],
      "priceSM": 7103,
      "row_id": 74
    },
    {
      "assetId": 80006857.0,
      "addressId": 53735412,
      "polygonId": "52301630",
      "neighborhoodName": "שבזי",
      "neighborhoodId": 65210556,
      "address": "אצ\"ל 93",
      "dealDate": "2006-12-21",
      "dealAmount": 606000,
      "parcelNum": "4270-50-1",
      "dealNature": "קוטג' חד משפחתי",
      "roomNum": 5.0,
      "floor": "שניה",
      "assetArea": 125.0,
      "yearBuilt": 1960,
      "streetCode": 26400184,
      "settlmentID": 2640,
      "buildingFloors": 0,
      "hokHamecher": 0,
      "prevDeals": [
        {
          "dealDate": "2004-12-29",
          "dealAmount": 787000
        }
      ],
      "trend": {
        "rate": -23.0,
        "years": 2.0
      },
      "ownership": [],
      "priceSM": 4848,
      "row_id": 75
    },
    {
      "assetId": 4092352.0,
      "addressId": 0,
      "polygonId": "4272-37",
      "neighborhoodName": "שבזי",
      "neighborhoodId": 65210556,
      "address": "0",
      "dealDate": "2005-12-27",
      "dealAmount": 576000,
      "parcelNum": "4272-37-4",
      "dealNature": "בית בודד",
      "roomNum": 3.0,
      "floor": null,
      "assetArea": 80.0,
      "yearBuilt": 0,
      "streetCode": 0,
      "settlmentID": 2640,
      "buildingFloors": 0,
      "hokHamecher": 0,
      "trend": {
        "rate": 0,
        "years": 0
      },
      "prevDeals": [],
      "ownership": [],
      "priceSM": 7200,
      "row_id": 76
    },
    {
      "assetId": 80007448.0,
      "addressId": 53735414,
      "polygonId": "53295038",
      "neighborhoodName": "שבזי",
      "neighborhoodId": 65210556,
      "address": "אפק 10",
      "dealDate": "2005-02-09",
      "dealAmount": 920000,
      "parcelNum": "4271-105-1",
      "dealNature": "קוטג' חד משפחתי",
      "roomNum": 4.0,
      "floor": null,
      "assetArea": 120.0,
      "yearBuilt": 2004,
      "streetCode": 26400143,
      "settlmentID": 2640,
      "buildingFloors": 0,
      "hokHamecher": 0,
      "trend": {
        "rate": 0,
        "years": 0
      },
      "prevDeals": [],
      "ownership": [],
      "priceSM": 7667,
      "row_id": 77
    },
    {
      "assetId": 4435729.0,
      "addressId": 53735463,
      "polygonId": "52324535",
      "neighborhoodName": "שבזי",
      "neighborhoodId": 65210556,
      "address": "יהודה הלוי 186",
      "dealDate": "2004-11-09",
      "dealAmount": 177000,
      "parcelNum": "4270-205-1",
      "dealNature": "בית בודד",
      "roomNum": 4.0,
      "floor": null,
      "assetArea": 86.0,
      "yearBuilt": 1960,
      "streetCode": 26400125,
      "settlmentID": 2640,
      "buildingFloors": 0,
      "hokHamecher": 0,
      "trend": {
        "rate": 0,
        "years": 0
      },
      "prevDeals": [],
      "ownership": [],
      "priceSM": 2058,
      "row_id": 78
    },
    {
      "assetId": 80007580.0,
      "addressId": 53907816,
      "polygonId": "53299249",
      "neighborhoodName": "שבזי",
      "neighborhoodId": 65210556,
      "address": "יורם חתוכה 13",
      "dealDate": "2004-08-25",
      "dealAmount": 920000,
      "parcelNum": "4271-141-2",
      "dealNature": "קוטג' דו משפחתי",
      "roomNum": 5.0,
      "floor": null,
      "assetArea": 140.0,
      "yearBuilt": 1995,
      "streetCode": 26400186,
      "settlmentID": 2640,
      "buildingFloors": 1,
      "hokHamecher": 0,
      "trend": {
        "rate": 0,
        "years": 0
      },
      "prevDeals": [],
      "ownership": [],
      "priceSM": 6571,
      "row_id": 79
    },
    {
      "assetId": 80006860.0,
      "addressId": 53735339,
      "polygonId": "52307042",
      "neighborhoodName": "שבזי",
      "neighborhoodId": 65210556,
      "address": "אפק 90",
      "dealDate": "2004-05-01",
      "dealAmount": 651000,
      "parcelNum": "4270-51-1",
      "dealNature": "בית בודד",
      "roomNum": 1.0,
      "floor": null,
      "assetArea": 21.87,
      "yearBuilt": 1960,
      "streetCode": 26400143,
      "settlmentID": 2640,
      "buildingFloors": 0,
      "hokHamecher": 0,
      "trend": {
        "rate": 0,
        "years": 0
      },
      "prevDeals": [],
      "ownership": [],
      "priceSM": 29767,
      "row_id": 80
    },
    {
      "assetId": 4090920.0,
      "addressId": 0,
      "polygonId": "4270-71",
      "neighborhoodName": "שבזי",
      "neighborhoodId": 65210556,
      "address": "0",
      "dealDate": "2003-12-31",
      "dealAmount": 1109000,
      "parcelNum": "4270-71-1",
      "dealNature": "קוטג' חד משפחתי",
      "roomNum": 3.0,
      "floor": null,
      "assetArea": 67.0,
      "yearBuilt": 0,
      "streetCode": 0,
      "settlmentID": 2640,
      "buildingFloors": 0,
      "hokHamecher": 0,
      "trend": {
        "rate": 0,
        "years": 0
      },
      "prevDeals": [],
      "ownership": [],
      "priceSM": 16552,
      "row_id": 81
    },
    {
      "assetId": 80006923.0,
      "addressId": 53728780,
      "polygonId": "71177236",
      "neighborhoodName": "שבזי",
      "neighborhoodId": 65210556,
      "address": "שבזי 112",
      "dealDate": "2003-06-01",
      "dealAmount": 787000,
      "parcelNum": "4270-69-1",
      "dealNature": "קוטג' חד משפחתי",
      "roomNum": 5.0,
      "floor": "ראשונה",
      "assetArea": 150.0,
      "yearBuilt": 1970,
      "streetCode": 26400142,
      "settlmentID": 2640,
      "buildingFloors": 0,
      "hokHamecher": 0,
      "trend": {
        "rate": 0,
        "years": 0
      },
      "prevDeals": [],
      "ownership": [],
      "priceSM": 5247,
      "row_id": 82
    }
  ]
}